Workbook

Sheet Sheet1
A1: company_name | B1: pic_name | C1: designation | D1: Number already exists in Master DB? contact_number1 | E1: Number already exists in Master DB? contact_number2 | F1: Number already exists in Master DB? contact_number3 | G1: Number already exists in Master DB? contact_number4 | H1: Number already exists in Master DB? contact_number5 | I1: Number already exists in Master DB? contact_number6 | J1: Number already exists in Master DB? contact_number7 | K1: Number already exists in Master DB? contact_number8 | L1: concat_contact_numbers | M1: contact_number 1 | N1: contact_number 2 | O1: contact_number 3 | P1: contact_number 4 | Q1: contact_number 5 | R1: contact_number 6 | S1: contact_number 7 | T1: contact_number 8 | U1: email_address | V1: address
A2: TAMJAI SAMGOR MIXIAN | B2: Micky Gan | D2: =COUNTIF('Duplicates_with_Master DB'!$A:$A,Sheet1!M2)>0 -> FALSE | E2: =COUNTIF('Duplicates_with_Master DB'!$A:$A,Sheet1!N2)>0 -> FALSE | F2: =COUNTIF('Duplicates_with_Master DB'!$A:$A,Sheet1!O2)>0 -> FALSE | G2: =COUNTIF('Duplicates_with_Master DB'!$A:$A,Sheet1!P2)>0 -> FALSE | H2: =COUNTIF('Duplicates_with_Master DB'!$A:$A,Sheet1!Q2)>0 -> FALSE | I2: =COUNTIF('Duplicates_with_Master DB'!$A:$A,Sheet1!R2)>0 -> FALSE | J2: =COUNTIF('Duplicates_with_Master DB'!$A:$A,Sheet1!S2)>0 -> FALSE | K2: =COUNTIF('Duplicates_with_Master DB'!$A:$A,Sheet1!T2)>0 -> FALSE | L2: =M2 & IF(COUNTA(N2:T2), ", " & _xlfn.TEXTJOIN(", ", TRUE, N2:T2), "") -> 65131787 | M2: 65131787 | U2: micky.gan@tamjai-inti.com.sg
A3: fair trade commodities | B3: melissa ang | D3: =COUNTIF('Duplicates_with_Master DB'!$A:$A,Sheet1!M3)>0 -> FALSE | E3: =COUNTIF('Duplicates_with_Master DB'!$A:$A,Sheet1!N3)>0 -> FALSE | F3: =COUNTIF('Duplicates_with_Master DB'!$A:$A,Sheet1!O3)>0 -> FALSE | G3: =COUNTIF('Duplicates_with_Master DB'!$A:$A,Sheet1!P3)>0 -> FALSE | H3: =COUNTIF('Duplicates_with_Master DB'!$A:$A,Sheet1!Q3)>0 -> FALSE | I3: =COUNTIF('Duplicates_with_Master DB'!$A:$A,Sheet1!R3)>0 -> FALSE | J3: =COUNTIF('Duplicates_with_Master DB'!$A:$A,Sheet1!S3)>0 -> FALSE | K3: =COUNTIF('Duplicates_with_Master DB'!$A:$A,Sheet1!T3)>0 -> FALSE | L3: =M3 & IF(COUNTA(N3:T3), ", " & _xlfn.TEXTJOIN(", ", TRUE, N3:T3), "") | U3: pa10.md@fairtradeasean.com
A4: forintech | B4: ian li | D4: =COUNTIF('Duplicates_with_Master DB'!$A:$A,Sheet1!M4)>0 -> FALSE | E4: =COUNTIF('Duplicates_with_Master DB'!$A:$A,Sheet1!N4)>0 -> FALSE | F4: =COUNTIF('Duplicates_with_Master DB'!$A:$A,Sheet1!O4)>0 -> FALSE | G4: =COUNTIF('Duplicates_with_Master DB'!$A:$A,Sheet1!P4)>0 -> FALSE | H4: =COUNTIF('Duplicates_with_Master DB'!$A:$A,Sheet1!Q4)>0 -> FALSE | I4: =COUNTIF('Duplicates_with_Master DB'!$A:$A,Sheet1!R4)>0 -> FALSE | J4: =COUNTIF('Duplicates_with_Master DB'!$A:$A,Sheet1!S4)>0 -> FALSE | K4: =COUNTIF('Duplicates_with_Master DB'!$A:$A,Sheet1!T4)>0 -> FALSE | L4: =M4 & IF(COUNTA(N4:T4), ", " & _xlfn.TEXTJOIN(", ", TRUE, N4:T4), "") -> 81323868 | M4: 81323868 | U4: ian.li@forintechasia.com
A5: culinarte | B5: rahul gladwin massey | D5: =COUNTIF('Duplicates_with_Master DB'!$A:$A,Sheet1!M5)>0 -> FALSE | E5: =COUNTIF('Duplicates_with_Master DB'!$A:$A,Sheet1!N5)>0 -> FALSE | F5: =COUNTIF('Duplicates_with_Master DB'!$A:$A,Sheet1!O5)>0 -> FALSE | G5: =COUNTIF('Duplicates_with_Master DB'!$A:$A,Sheet1!P5)>0 -> FALSE | H5: =COUNTIF('Duplicates_with_Master DB'!$A:$A,Sheet1!Q5)>0 -> FALSE | I5: =COUNTIF('Duplicates_with_Master DB'!$A:$A,Sheet1!R5)>0 -> FALSE | J5: =COUNTIF('Duplicates_with_Master DB'!$A:$A,Sheet1!S5)>0 -> FALSE | K5: =COUNTIF('Duplicates_with_Master DB'!$A:$A,Sheet1!T5)>0 -> FALSE | L5: =M5 & IF(COUNTA(N5:T5), ", " & _xlfn.TEXTJOIN(", ", TRUE, N5:T5), "") | U5: rahul@culinarte.in
A6: oxford acuity | B6: potnanee darakamas | D6: =COUNTIF('Duplicates_with_Master DB'!$A:$A,Sheet1!M6)>0 -> FALSE | E6: =COUNTIF('Duplicates_with_Master DB'!$A:$A,Sheet1!N6)>0 -> FALSE | F6: =COUNTIF('Duplicates_with_Master DB'!$A:$A,Sheet1!O6)>0 -> FALSE | G6: =COUNTIF('Duplicates_with_Master DB'!$A:$A,Sheet1!P6)>0 -> FALSE | H6: =COUNTIF('Duplicates_with_Master DB'!$A:$A,Sheet1!Q6)>0 -> FALSE | I6: =COUNTIF('Duplicates_with_Master DB'!$A:$A,Sheet1!R6)>0 -> FALSE | J6: =COUNTIF('Duplicates_with_Master DB'!$A:$A,Sheet1!S6)>0 -> FALSE | K6: =COUNTIF('Duplicates_with_Master DB'!$A:$A,Sheet1!T6)>0 -> FALSE | L6: =M6 & IF(COUNTA(N6:T6), ", " & _xlfn.TEXTJOIN(", ", TRUE, N6:T6), "") | U6: potjanee@oxfordacuity.com
A7: The Denzy Collective | B7: Kelvin toh | D7: =COUNTIF('Duplicates_with_Master DB'!$A:$A,Sheet1!M7)>0 -> FALSE | E7: =COUNTIF('Duplicates_with_Master DB'!$A:$A,Sheet1!N7)>0 -> FALSE | F7: =COUNTIF('Duplicates_with_Master DB'!$A:$A,Sheet1!O7)>0 -> FALSE | G7: =COUNTIF('Duplicates_with_Master DB'!$A:$A,Sheet1!P7)>0 -> FALSE | H7: =COUNTIF('Duplicates_with_Master DB'!$A:$A,Sheet1!Q7)>0 -> FALSE | I7: =COUNTIF('Duplicates_with_Master DB'!$A:$A,Sheet1!R7)>0 -> FALSE | J7: =COUNTIF('Duplicates_with_Master DB'!$A:$A,Sheet1!S7)>0 -> FALSE | K7: =COUNTIF('Duplicates_with_Master DB'!$A:$A,Sheet1!T7)>0 -> FALSE | L7: =M7 & IF(COUNTA(N7:T7), ", " & _xlfn.TEXTJOIN(", ", TRUE, N7:T7), "") -> 93864782 | M7: 93864782 | U7: kel@denzy.com
A8: international foodgnostic | B8: Richard Tay | D8: =COUNTIF('Duplicates_with_Master DB'!$A:$A,Sheet1!M8)>0 -> FALSE | E8: =COUNTIF('Duplicates_with_Master DB'!$A:$A,Sheet1!N8)>0 -> FALSE | F8: =COUNTIF('Duplicates_with_Master DB'!$A:$A,Sheet1!O8)>0 -> FALSE | G8: =COUNTIF('Duplicates_with_Master DB'!$A:$A,Sheet1!P8)>0 -> FALSE | H8: =COUNTIF('Duplicates_with_Master DB'!$A:$A,Sheet1!Q8)>0 -> FALSE | I8: =COUNTIF('Duplicates_with_Master DB'!$A:$A,Sheet1!R8)>0 -> FALSE | J8: =COUNTIF('Duplicates_with_Master DB'!$A:$A,Sheet1!S8)>0 -> FALSE | K8: =COUNTIF('Duplicates_with_Master DB'!$A:$A,Sheet1!T8)>0 -> FALSE | L8: =M8 & IF(COUNTA(N8:T8), ", " & _xlfn.TEXTJOIN(", ", TRUE, N8:T8), "") -> 96874191 | M8: 96874191 | U8: richard_tay@foodgnostic.com
A9: Hosanna freight and logistics pte ltd | B9: Yanti | D9: =COUNTIF('Duplicates_with_Master DB'!$A:$A,Sheet1!M9)>0 -> FALSE | E9: =COUNTIF('Duplicates_with_Master DB'!$A:$A,Sheet1!N9)>0 -> FALSE | F9: =COUNTIF('Duplicates_with_Master DB'!$A:$A,Sheet1!O9)>0 -> FALSE | G9: =COUNTIF('Duplicates_with_Master DB'!$A:$A,Sheet1!P9)>0 -> FALSE | H9: =COUNTIF('Duplicates_with_Master DB'!$A:$A,Sheet1!Q9)>0 -> FALSE | I9: =COUNTIF('Duplicates_with_Master DB'!$A:$A,Sheet1!R9)>0 -> FALSE | J9: =COUNTIF('Duplicates_with_Master DB'!$A:$A,Sheet1!S9)>0 -> FALSE | K9: =COUNTIF('Duplicates_with_Master DB'!$A:$A,Sheet1!T9)>0 -> FALSE | L9: =M9 & IF(COUNTA(N9:T9), ", " & _xlfn.TEXTJOIN(", ", TRUE, N9:T9), "") -> 96778810 | M9: 96778810 | U9: yanti.tang@hosannafreight.com.sg
A10: Yamato izakaya | B10: Ryan | D10: =COUNTIF('Duplicates_with_Master DB'!$A:$A,Sheet1!M10)>0 -> FALSE | E10: =COUNTIF('Duplicates_with_Master DB'!$A:$A,Sheet1!N10)>0 -> FALSE | F10: =COUNTIF('Duplicates_with_Master DB'!$A:$A,Sheet1!O10)>0 -> FALSE | G10: =COUNTIF('Duplicates_with_Master DB'!$A:$A,Sheet1!P10)>0 -> FALSE | H10: =COUNTIF('Duplicates_with_Master DB'!$A:$A,Sheet1!Q10)>0 -> FALSE | I10: =COUNTIF('Duplicates_with_Master DB'!$A:$A,Sheet1!R10)>0 -> FALSE | J10: =COUNTIF('Duplicates_with_Master DB'!$A:$A,Sheet1!S10)>0 -> FALSE | K10: =COUNTIF('Duplicates_with_Master DB'!$A:$A,Sheet1!T10)>0 -> FALSE | L10: =M10 & IF(COUNTA(N10:T10), ", " & _xlfn.TEXTJOIN(", ", TRUE, N10:T10), "") -> 97888918 | M10: 97888918 | U10: nil123@gmail.com
A11: Asiaworld Developments | B11: Genny chua | D11: =COUNTIF('Duplicates_with_Master DB'!$A:$A,Sheet1!M11)>0 -> FALSE | E11: =COUNTIF('Duplicates_with_Master DB'!$A:$A,Sheet1!N11)>0 -> FALSE | F11: =COUNTIF('Duplicates_with_Master DB'!$A:$A,Sheet1!O11)>0 -> FALSE | G11: =COUNTIF('Duplicates_with_Master DB'!$A:$A,Sheet1!P11)>0 -> FALSE | H11: =COUNTIF('Duplicates_with_Master DB'!$A:$A,Sheet1!Q11)>0 -> FALSE | I11: =COUNTIF('Duplicates_with_Master DB'!$A:$A,Sheet1!R11)>0 -> FALSE | J11: =COUNTIF('Duplicates_with_Master DB'!$A:$A,Sheet1!S11)>0 -> FALSE | K11: =COUNTIF('Duplicates_with_Master DB'!$A:$A,Sheet1!T11)>0 -> FALSE | L11: =M11 & IF(COUNTA(N11:T11), ", " & _xlfn.TEXTJOIN(", ", TRUE, N11:T11), "") -> 97325246 | M11: 97325246 | U11: asiaworld1000@yahoo.com
A12: Every Intl | B12: Andy Kuo | D12: =COUNTIF('Duplicates_with_Master DB'!$A:$A,Sheet1!M12)>0 -> FALSE | E12: =COUNTIF('Duplicates_with_Master DB'!$A:$A,Sheet1!N12)>0 -> FALSE | F12: =COUNTIF('Duplicates_with_Master DB'!$A:$A,Sheet1!O12)>0 -> FALSE | G12: =COUNTIF('Duplicates_with_Master DB'!$A:$A,Sheet1!P12)>0 -> FALSE | H12: =COUNTIF('Duplicates_with_Master DB'!$A:$A,Sheet1!Q12)>0 -> FALSE | I12: =COUNTIF('Duplicates_with_Master DB'!$A:$A,Sheet1!R12)>0 -> FALSE | J12: =COUNTIF('Duplicates_with_Master DB'!$A:$A,Sheet1!S12)>0 -> FALSE | K12: =COUNTIF('Duplicates_with_Master DB'!$A:$A,Sheet1!T12)>0 -> FALSE | L12: =M12 & IF(COUNTA(N12:T12), ", " & _xlfn.TEXTJOIN(", ", TRUE, N12:T12), "") -> 93821449 | M12: 93821449 | U12: andykuo76@gmail.com
A13: Läderach Chocolatier | B13: Alexander | D13: =COUNTIF('Duplicates_with_Master DB'!$A:$A,Sheet1!M13)>0 -> FALSE | E13: =COUNTIF('Duplicates_with_Master DB'!$A:$A,Sheet1!N13)>0 -> FALSE | F13: =COUNTIF('Duplicates_with_Master DB'!$A:$A,Sheet1!O13)>0 -> FALSE | G13: =COUNTIF('Duplicates_with_Master DB'!$A:$A,Sheet1!P13)>0 -> FALSE | H13: =COUNTIF('Duplicates_with_Master DB'!$A:$A,Sheet1!Q13)>0 -> FALSE | I13: =COUNTIF('Duplicates_with_Master DB'!$A:$A,Sheet1!R13)>0 -> FALSE | J13: =COUNTIF('Duplicates_with_Master DB'!$A:$A,Sheet1!S13)>0 -> FALSE | K13: =COUNTIF('Duplicates_with_Master DB'!$A:$A,Sheet1!T13)>0 -> FALSE | L13: =M13 & IF(COUNTA(N13:T13), ", " & _xlfn.TEXTJOIN(", ", TRUE, N13:T13), "") -> 98161222 | M13: 98161222 | U13: operations@laderach.com.sg
A14: Shinagi | B14: Iwan | D14: =COUNTIF('Duplicates_with_Master DB'!$A:$A,Sheet1!M14)>0 -> FALSE | E14: =COUNTIF('Duplicates_with_Master DB'!$A:$A,Sheet1!N14)>0 -> FALSE | F14: =COUNTIF('Duplicates_with_Master DB'!$A:$A,Sheet1!O14)>0 -> FALSE | G14: =COUNTIF('Duplicates_with_Master DB'!$A:$A,Sheet1!P14)>0 -> FALSE | H14: =COUNTIF('Duplicates_with_Master DB'!$A:$A,Sheet1!Q14)>0 -> FALSE | I14: =COUNTIF('Duplicates_with_Master DB'!$A:$A,Sheet1!R14)>0 -> FALSE | J14: =COUNTIF('Duplicates_with_Master DB'!$A:$A,Sheet1!S14)>0 -> FALSE | K14: =COUNTIF('Duplicates_with_Master DB'!$A:$A,Sheet1!T14)>0 -> FALSE | L14: =M14 & IF(COUNTA(N14:T14), ", " & _xlfn.TEXTJOIN(", ", TRUE, N14:T14), "") -> 93403891 | M14: 93403891 | U14: iwan.golf@yahoo.com
A15: Toho Singapore | B15: Takizawa Ritsuko | D15: =COUNTIF('Duplicates_with_Master DB'!$A:$A,Sheet1!M15)>0 -> FALSE | E15: =COUNTIF('Duplicates_with_Master DB'!$A:$A,Sheet1!N15)>0 -> FALSE | F15: =COUNTIF('Duplicates_with_Master DB'!$A:$A,Sheet1!O15)>0 -> FALSE | G15: =COUNTIF('Duplicates_with_Master DB'!$A:$A,Sheet1!P15)>0 -> FALSE | H15: =COUNTIF('Duplicates_with_Master DB'!$A:$A,Sheet1!Q15)>0 -> FALSE | I15: =COUNTIF('Duplicates_with_Master DB'!$A:$A,Sheet1!R15)>0 -> FALSE | J15: =COUNTIF('Duplicates_with_Master DB'!$A:$A,Sheet1!S15)>0 -> FALSE | K15: =COUNTIF('Duplicates_with_Master DB'!$A:$A,Sheet1!T15)>0 -> FALSE | L15: =M15 & IF(COUNTA(N15:T15), ", " & _xlfn.TEXTJOIN(", ", TRUE, N15:T15), "") -> 90939387 | M15: 90939387 | U15: takizawa@to-ho.com.sg
A16: The Tasting Room by Ikon Mart | B16: Aung Than Htay | D16: =COUNTIF('Duplicates_with_Master DB'!$A:$A,Sheet1!M16)>0 -> FALSE | E16: =COUNTIF('Duplicates_with_Master DB'!$A:$A,Sheet1!N16)>0 -> FALSE | F16: =COUNTIF('Duplicates_with_Master DB'!$A:$A,Sheet1!O16)>0 -> FALSE | G16: =COUNTIF('Duplicates_with_Master DB'!$A:$A,Sheet1!P16)>0 -> FALSE | H16: =COUNTIF('Duplicates_with_Master DB'!$A:$A,Sheet1!Q16)>0 -> FALSE | I16: =COUNTIF('Duplicates_with_Master DB'!$A:$A,Sheet1!R16)>0 -> FALSE | J16: =COUNTIF('Duplicates_with_Master DB'!$A:$A,Sheet1!S16)>0 -> FALSE | K16: =COUNTIF('Duplicates_with_Master DB'!$A:$A,Sheet1!T16)>0 -> FALSE | L16: =M16 & IF(COUNTA(N16:T16), ", " & _xlfn.TEXTJOIN(", ", TRUE, N16:T16), "") | U16: ath@ikonmart.com
A17: Food joy | B17: Linus | D17: =COUNTIF('Duplicates_with_Master DB'!$A:$A,Sheet1!M17)>0 -> FALSE | E17: =COUNTIF('Duplicates_with_Master DB'!$A:$A,Sheet1!N17)>0 -> FALSE | F17: =COUNTIF('Duplicates_with_Master DB'!$A:$A,Sheet1!O17)>0 -> FALSE | G17: =COUNTIF('Duplicates_with_Master DB'!$A:$A,Sheet1!P17)>0 -> FALSE | H17: =COUNTIF('Duplicates_with_Master DB'!$A:$A,Sheet1!Q17)>0 -> FALSE | I17: =COUNTIF('Duplicates_with_Master DB'!$A:$A,Sheet1!R17)>0 -> FALSE | J17: =COUNTIF('Duplicates_with_Master DB'!$A:$A,Sheet1!S17)>0 -> FALSE | K17: =COUNTIF('Duplicates_with_Master DB'!$A:$A,Sheet1!T17)>0 -> FALSE | L17: =M17 & IF(COUNTA(N17:T17), ", " & _xlfn.TEXTJOIN(", ", TRUE, N17:T17), "") -> 84995150 | M17: 84995150 | U17: linus.low@bluecube.com.sg
A18: Tiong Hoe Specialty Coffee | B18: Juliana | D18: =COUNTIF('Duplicates_with_Master DB'!$A:$A,Sheet1!M18)>0 -> FALSE | E18: =COUNTIF('Duplicates_with_Master DB'!$A:$A,Sheet1!N18)>0 -> FALSE | F18: =COUNTIF('Duplicates_with_Master DB'!$A:$A,Sheet1!O18)>0 -> FALSE | G18: =COUNTIF('Duplicates_with_Master DB'!$A:$A,Sheet1!P18)>0 -> FALSE | H18: =COUNTIF('Duplicates_with_Master DB'!$A:$A,Sheet1!Q18)>0 -> FALSE | I18: =COUNTIF('Duplicates_with_Master DB'!$A:$A,Sheet1!R18)>0 -> FALSE | J18: =COUNTIF('Duplicates_with_Master DB'!$A:$A,Sheet1!S18)>0 -> FALSE | K18: =COUNTIF('Duplicates_with_Master DB'!$A:$A,Sheet1!T18)>0 -> FALSE | L18: =M18 & IF(COUNTA(N18:T18), ", " & _xlfn.TEXTJOIN(", ", TRUE, N18:T18), "") -> 91299697 | M18: 91299697 | U18: accounts@tionghoe.com
A19: Niveken Pte ltd | B19: Kevin | D19: =COUNTIF('Duplicates_with_Master DB'!$A:$A,Sheet1!M19)>0 -> FALSE | E19: =COUNTIF('Duplicates_with_Master DB'!$A:$A,Sheet1!N19)>0 -> FALSE | F19: =COUNTIF('Duplicates_with_Master DB'!$A:$A,Sheet1!O19)>0 -> FALSE | G19: =COUNTIF('Duplicates_with_Master DB'!$A:$A,Sheet1!P19)>0 -> FALSE | H19: =COUNTIF('Duplicates_with_Master DB'!$A:$A,Sheet1!Q19)>0 -> FALSE | I19: =COUNTIF('Duplicates_with_Master DB'!$A:$A,Sheet1!R19)>0 -> FALSE | J19: =COUNTIF('Duplicates_with_Master DB'!$A:$A,Sheet1!S19)>0 -> FALSE | K19: =COUNTIF('Duplicates_with_Master DB'!$A:$A,Sheet1!T19)>0 -> FALSE | L19: =M19 & IF(COUNTA(N19:T19), ", " & _xlfn.TEXTJOIN(", ", TRUE, N19:T19), "") -> 96891318 | M19: 96891318 | U19: kevin@niveken.com
A20: Restaurant Brands International | B20: Yu Shan | D20: =COUNTIF('Duplicates_with_Master DB'!$A:$A,Sheet1!M20)>0 -> FALSE | E20: =COUNTIF('Duplicates_with_Master DB'!$A:$A,Sheet1!N20)>0 -> FALSE | F20: =COUNTIF('Duplicates_with_Master DB'!$A:$A,Sheet1!O20)>0 -> FALSE | G20: =COUNTIF('Duplicates_with_Master DB'!$A:$A,Sheet1!P20)>0 -> FALSE | H20: =COUNTIF('Duplicates_with_Master DB'!$A:$A,Sheet1!Q20)>0 -> FALSE | I20: =COUNTIF('Duplicates_with_Master DB'!$A:$A,Sheet1!R20)>0 -> FALSE | J20: =COUNTIF('Duplicates_with_Master DB'!$A:$A,Sheet1!S20)>0 -> FALSE | K20: =COUNTIF('Duplicates_with_Master DB'!$A:$A,Sheet1!T20)>0 -> FALSE | L20: =M20 & IF(COUNTA(N20:T20), ", " & _xlfn.TEXTJOIN(", ", TRUE, N20:T20), "") -> 83485931 | M20: 83485931 | U20: yushan9513@gmail.com
A21: Best food | B21: Donald Yap | D21: =COUNTIF('Duplicates_with_Master DB'!$A:$A,Sheet1!M21)>0 -> FALSE | E21: =COUNTIF('Duplicates_with_Master DB'!$A:$A,Sheet1!N21)>0 -> FALSE | F21: =COUNTIF('Duplicates_with_Master DB'!$A:$A,Sheet1!O21)>0 -> FALSE | G21: =COUNTIF('Duplicates_with_Master DB'!$A:$A,Sheet1!P21)>0 -> FALSE | H21: =COUNTIF('Duplicates_with_Master DB'!$A:$A,Sheet1!Q21)>0 -> FALSE | I21: =COUNTIF('Duplicates_with_Master DB'!$A:$A,Sheet1!R21)>0 -> FALSE | J21: =COUNTIF('Duplicates_with_Master DB'!$A:$A,Sheet1!S21)>0 -> FALSE | K21: =COUNTIF('Duplicates_with_Master DB'!$A:$A,Sheet1!T21)>0 -> FALSE | L21: =M21 & IF(COUNTA(N21:T21), ", " & _xlfn.TEXTJOIN(", ", TRUE, N21:T21), "") | U21: donald@hzgreenpulp.com
A22: mok corner | B22: Jacky | D22: =COUNTIF('Duplicates_with_Master DB'!$A:$A,Sheet1!M22)>0 -> FALSE | E22: =COUNTIF('Duplicates_with_Master DB'!$A:$A,Sheet1!N22)>0 -> FALSE | F22: =COUNTIF('Duplicates_with_Master DB'!$A:$A,Sheet1!O22)>0 -> FALSE | G22: =COUNTIF('Duplicates_with_Master DB'!$A:$A,Sheet1!P22)>0 -> FALSE | H22: =COUNTIF('Duplicates_with_Master DB'!$A:$A,Sheet1!Q22)>0 -> FALSE | I22: =COUNTIF('Duplicates_with_Master DB'!$A:$A,Sheet1!R22)>0 -> FALSE | J22: =COUNTIF('Duplicates_with_Master DB'!$A:$A,Sheet1!S22)>0 -> FALSE | K22: =COUNTIF('Duplicates_with_Master DB'!$A:$A,Sheet1!T22)>0 -> FALSE | L22: =M22 & IF(COUNTA(N22:T22), ", " & _xlfn.TEXTJOIN(", ", TRUE, N22:T22), "") | U22: jackychin@mokcorner.com
A23: Wok hey | B23: Kaidi | D23: =COUNTIF('Duplicates_with_Master DB'!$A:$A,Sheet1!M23)>0 -> FALSE | E23: =COUNTIF('Duplicates_with_Master DB'!$A:$A,Sheet1!N23)>0 -> FALSE | F23: =COUNTIF('Duplicates_with_Master DB'!$A:$A,Sheet1!O23)>0 -> FALSE | G23: =COUNTIF('Duplicates_with_Master DB'!$A:$A,Sheet1!P23)>0 -> FALSE | H23: =COUNTIF('Duplicates_with_Master DB'!$A:$A,Sheet1!Q23)>0 -> FALSE | I23: =COUNTIF('Duplicates_with_Master DB'!$A:$A,Sheet1!R23)>0 -> FALSE | J23: =COUNTIF('Duplicates_with_Master DB'!$A:$A,Sheet1!S23)>0 -> FALSE | K23: =COUNTIF('Duplicates_with_Master DB'!$A:$A,Sheet1!T23)>0 -> FALSE | L23: =M23 & IF(COUNTA(N23:T23), ", " & _xlfn.TEXTJOIN(", ", TRUE, N23:T23), "") -> 81869437 | M23: 81869437 | U23: kaidi@wokhey.sg
A24: Mintplus | B24: Shen | D24: =COUNTIF('Duplicates_with_Master DB'!$A:$A,Sheet1!M24)>0 -> FALSE | E24: =COUNTIF('Duplicates_with_Master DB'!$A:$A,Sheet1!N24)>0 -> FALSE | F24: =COUNTIF('Duplicates_with_Master DB'!$A:$A,Sheet1!O24)>0 -> FALSE | G24: =COUNTIF('Duplicates_with_Master DB'!$A:$A,Sheet1!P24)>0 -> FALSE | H24: =COUNTIF('Duplicates_with_Master DB'!$A:$A,Sheet1!Q24)>0 -> FALSE | I24: =COUNTIF('Duplicates_with_Master DB'!$A:$A,Sheet1!R24)>0 -> FALSE | J24: =COUNTIF('Duplicates_with_Master DB'!$A:$A,Sheet1!S24)>0 -> FALSE | K24: =COUNTIF('Duplicates_with_Master DB'!$A:$A,Sheet1!T24)>0 -> FALSE | L24: =M24 & IF(COUNTA(N24:T24), ", " & _xlfn.TEXTJOIN(", ", TRUE, N24:T24), "") -> 90359556 | M24: 90359556 | U24: shine10607@126.com
A25: eG Innovations | B25: Adan Yap | D25: =COUNTIF('Duplicates_with_Master DB'!$A:$A,Sheet1!M25)>0 -> FALSE | E25: =COUNTIF('Duplicates_with_Master DB'!$A:$A,Sheet1!N25)>0 -> FALSE | F25: =COUNTIF('Duplicates_with_Master DB'!$A:$A,Sheet1!O25)>0 -> FALSE | G25: =COUNTIF('Duplicates_with_Master DB'!$A:$A,Sheet1!P25)>0 -> FALSE | H25: =COUNTIF('Duplicates_with_Master DB'!$A:$A,Sheet1!Q25)>0 -> FALSE | I25: =COUNTIF('Duplicates_with_Master DB'!$A:$A,Sheet1!R25)>0 -> FALSE | J25: =COUNTIF('Duplicates_with_Master DB'!$A:$A,Sheet1!S25)>0 -> FALSE | K25: =COUNTIF('Duplicates_with_Master DB'!$A:$A,Sheet1!T25)>0 -> FALSE | L25: =M25 & IF(COUNTA(N25:T25), ", " & _xlfn.TEXTJOIN(", ", TRUE, N25:T25), "") -> 97389832 | M25: 97389832 | U25: adan.yap@eginnovations.com
A26: Westlake | B26: Matthew Lim | D26: =COUNTIF('Duplicates_with_Master DB'!$A:$A,Sheet1!M26)>0 -> FALSE | E26: =COUNTIF('Duplicates_with_Master DB'!$A:$A,Sheet1!N26)>0 -> FALSE | F26: =COUNTIF('Duplicates_with_Master DB'!$A:$A,Sheet1!O26)>0 -> FALSE | G26: =COUNTIF('Duplicates_with_Master DB'!$A:$A,Sheet1!P26)>0 -> FALSE | H26: =COUNTIF('Duplicates_with_Master DB'!$A:$A,Sheet1!Q26)>0 -> FALSE | I26: =COUNTIF('Duplicates_with_Master DB'!$A:$A,Sheet1!R26)>0 -> FALSE | J26: =COUNTIF('Duplicates_with_Master DB'!$A:$A,Sheet1!S26)>0 -> FALSE | K26: =COUNTIF('Duplicates_with_Master DB'!$A:$A,Sheet1!T26)>0 -> FALSE | L26: =M26 & IF(COUNTA(N26:T26), ", " & _xlfn.TEXTJOIN(", ", TRUE, N26:T26), "") -> 97495989 | M26: 97495989 | U26: matthew.lim@westlake.com.sg
A27: LAGNAA barefoot dining | B27: RAJAKUMARI | D27: =COUNTIF('Duplicates_with_Master DB'!$A:$A,Sheet1!M27)>0 -> FALSE | E27: =COUNTIF('Duplicates_with_Master DB'!$A:$A,Sheet1!N27)>0 -> FALSE | F27: =COUNTIF('Duplicates_with_Master DB'!$A:$A,Sheet1!O27)>0 -> FALSE | G27: =COUNTIF('Duplicates_with_Master DB'!$A:$A,Sheet1!P27)>0 -> FALSE | H27: =COUNTIF('Duplicates_with_Master DB'!$A:$A,Sheet1!Q27)>0 -> FALSE | I27: =COUNTIF('Duplicates_with_Master DB'!$A:$A,Sheet1!R27)>0 -> FALSE | J27: =COUNTIF('Duplicates_with_Master DB'!$A:$A,Sheet1!S27)>0 -> FALSE | K27: =COUNTIF('Duplicates_with_Master DB'!$A:$A,Sheet1!T27)>0 -> FALSE | L27: =M27 & IF(COUNTA(N27:T27), ", " & _xlfn.TEXTJOIN(", ", TRUE, N27:T27), "") -> 92399702 | M27: 92399702 | U27: barefootdining@lagnaa.com
A28: Mr kneady | B28: Lionel | D28: =COUNTIF('Duplicates_with_Master DB'!$A:$A,Sheet1!M28)>0 -> FALSE | E28: =COUNTIF('Duplicates_with_Master DB'!$A:$A,Sheet1!N28)>0 -> FALSE | F28: =COUNTIF('Duplicates_with_Master DB'!$A:$A,Sheet1!O28)>0 -> FALSE | G28: =COUNTIF('Duplicates_with_Master DB'!$A:$A,Sheet1!P28)>0 -> FALSE | H28: =COUNTIF('Duplicates_with_Master DB'!$A:$A,Sheet1!Q28)>0 -> FALSE | I28: =COUNTIF('Duplicates_with_Master DB'!$A:$A,Sheet1!R28)>0 -> FALSE | J28: =COUNTIF('Duplicates_with_Master DB'!$A:$A,Sheet1!S28)>0 -> FALSE | K28: =COUNTIF('Duplicates_with_Master DB'!$A:$A,Sheet1!T28)>0 -> FALSE | L28: =M28 & IF(COUNTA(N28:T28), ", " & _xlfn.TEXTJOIN(", ", TRUE, N28:T28), "") -> 91718507 | M28: 91718507 | U28: mrkneadys@gmail.com
A29: Chuanwei | B29: Soon | D29: =COUNTIF('Duplicates_with_Master DB'!$A:$A,Sheet1!M29)>0 -> FALSE | E29: =COUNTIF('Duplicates_with_Master DB'!$A:$A,Sheet1!N29)>0 -> FALSE | F29: =COUNTIF('Duplicates_with_Master DB'!$A:$A,Sheet1!O29)>0 -> FALSE | G29: =COUNTIF('Duplicates_with_Master DB'!$A:$A,Sheet1!P29)>0 -> FALSE | H29: =COUNTIF('Duplicates_with_Master DB'!$A:$A,Sheet1!Q29)>0 -> FALSE | I29: =COUNTIF('Duplicates_with_Master DB'!$A:$A,Sheet1!R29)>0 -> FALSE | J29: =COUNTIF('Duplicates_with_Master DB'!$A:$A,Sheet1!S29)>0 -> FALSE | K29: =COUNTIF('Duplicates_with_Master DB'!$A:$A,Sheet1!T29)>0 -> FALSE | L29: =M29 & IF(COUNTA(N29:T29), ", " & _xlfn.TEXTJOIN(", ", TRUE, N29:T29), "") -> 87231077 | M29: 87231077 | U29: torres6994331@hotmail.com
A30: Mikigold Intl | B30: Michael Goh | D30: =COUNTIF('Duplicates_with_Master DB'!$A:$A,Sheet1!M30)>0 -> FALSE | E30: =COUNTIF('Duplicates_with_Master DB'!$A:$A,Sheet1!N30)>0 -> FALSE | F30: =COUNTIF('Duplicates_with_Master DB'!$A:$A,Sheet1!O30)>0 -> FALSE | G30: =COUNTIF('Duplicates_with_Master DB'!$A:$A,Sheet1!P30)>0 -> FALSE | H30: =COUNTIF('Duplicates_with_Master DB'!$A:$A,Sheet1!Q30)>0 -> FALSE | I30: =COUNTIF('Duplicates_with_Master DB'!$A:$A,Sheet1!R30)>0 -> FALSE | J30: =COUNTIF('Duplicates_with_Master DB'!$A:$A,Sheet1!S30)>0 -> FALSE | K30: =COUNTIF('Duplicates_with_Master DB'!$A:$A,Sheet1!T30)>0 -> FALSE | L30: =M30 & IF(COUNTA(N30:T30), ", " & _xlfn.TEXTJOIN(", ", TRUE, N30:T30), "") -> 96452781 | M30: 96452781 | U30: mikigold8@yahoo.com
A31: Bbq master | B31: Wang Shuang | D31: =COUNTIF('Duplicates_with_Master DB'!$A:$A,Sheet1!M31)>0 -> FALSE | E31: =COUNTIF('Duplicates_with_Master DB'!$A:$A,Sheet1!N31)>0 -> FALSE | F31: =COUNTIF('Duplicates_with_Master DB'!$A:$A,Sheet1!O31)>0 -> FALSE | G31: =COUNTIF('Duplicates_with_Master DB'!$A:$A,Sheet1!P31)>0 -> FALSE | H31: =COUNTIF('Duplicates_with_Master DB'!$A:$A,Sheet1!Q31)>0 -> FALSE | I31: =COUNTIF('Duplicates_with_Master DB'!$A:$A,Sheet1!R31)>0 -> FALSE | J31: =COUNTIF('Duplicates_with_Master DB'!$A:$A,Sheet1!S31)>0 -> FALSE | K31: =COUNTIF('Duplicates_with_Master DB'!$A:$A,Sheet1!T31)>0 -> FALSE | L31: =M31 & IF(COUNTA(N31:T31), ", " & _xlfn.TEXTJOIN(", ", TRUE, N31:T31), "") -> 83835380 | M31: 83835380 | U31: aiwinnie@hotmail.com
A32: Innergia Labs | B32: Jack Lim | D32: =COUNTIF('Duplicates_with_Master DB'!$A:$A,Sheet1!M32)>0 -> FALSE | E32: =COUNTIF('Duplicates_with_Master DB'!$A:$A,Sheet1!N32)>0 -> FALSE | F32: =COUNTIF('Duplicates_with_Master DB'!$A:$A,Sheet1!O32)>0 -> FALSE | G32: =COUNTIF('Duplicates_with_Master DB'!$A:$A,Sheet1!P32)>0 -> FALSE | H32: =COUNTIF('Duplicates_with_Master DB'!$A:$A,Sheet1!Q32)>0 -> FALSE | I32: =COUNTIF('Duplicates_with_Master DB'!$A:$A,Sheet1!R32)>0 -> FALSE | J32: =COUNTIF('Duplicates_with_Master DB'!$A:$A,Sheet1!S32)>0 -> FALSE | K32: =COUNTIF('Duplicates_with_Master DB'!$A:$A,Sheet1!T32)>0 -> FALSE | L32: =M32 & IF(COUNTA(N32:T32), ", " & _xlfn.TEXTJOIN(", ", TRUE, N32:T32), "") -> 93834249 | M32: 93834249 | U32: jack@sycarda.ai
A33: Unimas Consulting Solutions Pte Ltd | B33: Muru | D33: =COUNTIF('Duplicates_with_Master DB'!$A:$A,Sheet1!M33)>0 -> FALSE | E33: =COUNTIF('Duplicates_with_Master DB'!$A:$A,Sheet1!N33)>0 -> FALSE | F33: =COUNTIF('Duplicates_with_Master DB'!$A:$A,Sheet1!O33)>0 -> FALSE | G33: =COUNTIF('Duplicates_with_Master DB'!$A:$A,Sheet1!P33)>0 -> FALSE | H33: =COUNTIF('Duplicates_with_Master DB'!$A:$A,Sheet1!Q33)>0 -> FALSE | I33: =COUNTIF('Duplicates_with_Master DB'!$A:$A,Sheet1!R33)>0 -> FALSE | J33: =COUNTIF('Duplicates_with_Master DB'!$A:$A,Sheet1!S33)>0 -> FALSE | K33: =COUNTIF('Duplicates_with_Master DB'!$A:$A,Sheet1!T33)>0 -> FALSE | L33: =M33 & IF(COUNTA(N33:T33), ", " & _xlfn.TEXTJOIN(", ", TRUE, N33:T33), "") | U33: cm.anand@outlook.com
A34: INNovate QrLock Pte Ltd | B34: Miko | D34: =COUNTIF('Duplicates_with_Master DB'!$A:$A,Sheet1!M34)>0 -> FALSE | E34: =COUNTIF('Duplicates_with_Master DB'!$A:$A,Sheet1!N34)>0 -> FALSE | F34: =COUNTIF('Duplicates_with_Master DB'!$A:$A,Sheet1!O34)>0 -> FALSE | G34: =COUNTIF('Duplicates_with_Master DB'!$A:$A,Sheet1!P34)>0 -> FALSE | H34: =COUNTIF('Duplicates_with_Master DB'!$A:$A,Sheet1!Q34)>0 -> FALSE | I34: =COUNTIF('Duplicates_with_Master DB'!$A:$A,Sheet1!R34)>0 -> FALSE | J34: =COUNTIF('Duplicates_with_Master DB'!$A:$A,Sheet1!S34)>0 -> FALSE | K34: =COUNTIF('Duplicates_with_Master DB'!$A:$A,Sheet1!T34)>0 -> FALSE | L34: =M34 & IF(COUNTA(N34:T34), ", " & _xlfn.TEXTJOIN(", ", TRUE, N34:T34), "") -> 98383655 | M34: 98383655 | U34: sales2qrlock@outlook.com
A35: far east | B35: Elisa chew | D35: =COUNTIF('Duplicates_with_Master DB'!$A:$A,Sheet1!M35)>0 -> FALSE | E35: =COUNTIF('Duplicates_with_Master DB'!$A:$A,Sheet1!N35)>0 -> FALSE | F35: =COUNTIF('Duplicates_with_Master DB'!$A:$A,Sheet1!O35)>0 -> FALSE | G35: =COUNTIF('Duplicates_with_Master DB'!$A:$A,Sheet1!P35)>0 -> FALSE | H35: =COUNTIF('Duplicates_with_Master DB'!$A:$A,Sheet1!Q35)>0 -> FALSE | I35: =COUNTIF('Duplicates_with_Master DB'!$A:$A,Sheet1!R35)>0 -> FALSE | J35: =COUNTIF('Duplicates_with_Master DB'!$A:$A,Sheet1!S35)>0 -> FALSE | K35: =COUNTIF('Duplicates_with_Master DB'!$A:$A,Sheet1!T35)>0 -> FALSE | L35: =M35 & IF(COUNTA(N35:T35), ", " & _xlfn.TEXTJOIN(", ", TRUE, N35:T35), "") -> 91138102 | M35: 91138102 | U35: elisachew@fareast.com.sg
A36: maslina | B36: ms nazilah nasir | D36: =COUNTIF('Duplicates_with_Master DB'!$A:$A,Sheet1!M36)>0 -> FALSE | E36: =COUNTIF('Duplicates_with_Master DB'!$A:$A,Sheet1!N36)>0 -> FALSE | F36: =COUNTIF('Duplicates_with_Master DB'!$A:$A,Sheet1!O36)>0 -> FALSE | G36: =COUNTIF('Duplicates_with_Master DB'!$A:$A,Sheet1!P36)>0 -> FALSE | H36: =COUNTIF('Duplicates_with_Master DB'!$A:$A,Sheet1!Q36)>0 -> FALSE | I36: =COUNTIF('Duplicates_with_Master DB'!$A:$A,Sheet1!R36)>0 -> FALSE | J36: =COUNTIF('Duplicates_with_Master DB'!$A:$A,Sheet1!S36)>0 -> FALSE | K36: =COUNTIF('Duplicates_with_Master DB'!$A:$A,Sheet1!T36)>0 -> FALSE | L36: =M36 & IF(COUNTA(N36:T36), ", " & _xlfn.TEXTJOIN(", ", TRUE, N36:T36), "") -> 97515612 | M36: 97515612 | U36: marketing@delimaslina.com
A37: Vino sg | B37: Amith Anand | D37: =COUNTIF('Duplicates_with_Master DB'!$A:$A,Sheet1!M37)>0 -> FALSE | E37: =COUNTIF('Duplicates_with_Master DB'!$A:$A,Sheet1!N37)>0 -> FALSE | F37: =COUNTIF('Duplicates_with_Master DB'!$A:$A,Sheet1!O37)>0 -> FALSE | G37: =COUNTIF('Duplicates_with_Master DB'!$A:$A,Sheet1!P37)>0 -> FALSE | H37: =COUNTIF('Duplicates_with_Master DB'!$A:$A,Sheet1!Q37)>0 -> FALSE | I37: =COUNTIF('Duplicates_with_Master DB'!$A:$A,Sheet1!R37)>0 -> FALSE | J37: =COUNTIF('Duplicates_with_Master DB'!$A:$A,Sheet1!S37)>0 -> FALSE | K37: =COUNTIF('Duplicates_with_Master DB'!$A:$A,Sheet1!T37)>0 -> FALSE | L37: =M37 & IF(COUNTA(N37:T37), ", " & _xlfn.TEXTJOIN(", ", TRUE, N37:T37), "") -> 83390169 | M37: 83390169 | U37: contact@vino.sg
A38: Real inbound consulting | B38: Hayley Heah | D38: =COUNTIF('Duplicates_with_Master DB'!$A:$A,Sheet1!M38)>0 -> FALSE | E38: =COUNTIF('Duplicates_with_Master DB'!$A:$A,Sheet1!N38)>0 -> FALSE | F38: =COUNTIF('Duplicates_with_Master DB'!$A:$A,Sheet1!O38)>0 -> FALSE | G38: =COUNTIF('Duplicates_with_Master DB'!$A:$A,Sheet1!P38)>0 -> FALSE | H38: =COUNTIF('Duplicates_with_Master DB'!$A:$A,Sheet1!Q38)>0 -> FALSE | I38: =COUNTIF('Duplicates_with_Master DB'!$A:$A,Sheet1!R38)>0 -> FALSE | J38: =COUNTIF('Duplicates_with_Master DB'!$A:$A,Sheet1!S38)>0 -> FALSE | K38: =COUNTIF('Duplicates_with_Master DB'!$A:$A,Sheet1!T38)>0 -> FALSE | L38: =M38 & IF(COUNTA(N38:T38), ", " & _xlfn.TEXTJOIN(", ", TRUE, N38:T38), "") -> 83099505 | M38: 83099505 | U38: hayley@realinboundconsulting.com
A39: Marina Bay sands | B39: Eugene Chow | D39: =COUNTIF('Duplicates_with_Master DB'!$A:$A,Sheet1!M39)>0 -> FALSE | E39: =COUNTIF('Duplicates_with_Master DB'!$A:$A,Sheet1!N39)>0 -> FALSE | F39: =COUNTIF('Duplicates_with_Master DB'!$A:$A,Sheet1!O39)>0 -> FALSE | G39: =COUNTIF('Duplicates_with_Master DB'!$A:$A,Sheet1!P39)>0 -> FALSE | H39: =COUNTIF('Duplicates_with_Master DB'!$A:$A,Sheet1!Q39)>0 -> FALSE | I39: =COUNTIF('Duplicates_with_Master DB'!$A:$A,Sheet1!R39)>0 -> FALSE | J39: =COUNTIF('Duplicates_with_Master DB'!$A:$A,Sheet1!S39)>0 -> FALSE | K39: =COUNTIF('Duplicates_with_Master DB'!$A:$A,Sheet1!T39)>0 -> FALSE | L39: =M39 & IF(COUNTA(N39:T39), ", " & _xlfn.TEXTJOIN(", ", TRUE, N39:T39), "") -> 83280239 | M39: 83280239 | U39: eugene.chow@marinabaysands.com
A40: Cowpresso | B40: David | D40: =COUNTIF('Duplicates_with_Master DB'!$A:$A,Sheet1!M40)>0 -> FALSE | E40: =COUNTIF('Duplicates_with_Master DB'!$A:$A,Sheet1!N40)>0 -> FALSE | F40: =COUNTIF('Duplicates_with_Master DB'!$A:$A,Sheet1!O40)>0 -> FALSE | G40: =COUNTIF('Duplicates_with_Master DB'!$A:$A,Sheet1!P40)>0 -> FALSE | H40: =COUNTIF('Duplicates_with_Master DB'!$A:$A,Sheet1!Q40)>0 -> FALSE | I40: =COUNTIF('Duplicates_with_Master DB'!$A:$A,Sheet1!R40)>0 -> FALSE | J40: =COUNTIF('Duplicates_with_Master DB'!$A:$A,Sheet1!S40)>0 -> FALSE | K40: =COUNTIF('Duplicates_with_Master DB'!$A:$A,Sheet1!T40)>0 -> FALSE | L40: =M40 & IF(COUNTA(N40:T40), ", " & _xlfn.TEXTJOIN(", ", TRUE, N40:T40), "") -> 94300464 | M40: 94300464 | U40: david@cowpressocoffee.sg
A41: Tang Tea House | B41: Clarence | D41: =COUNTIF('Duplicates_with_Master DB'!$A:$A,Sheet1!M41)>0 -> FALSE | E41: =COUNTIF('Duplicates_with_Master DB'!$A:$A,Sheet1!N41)>0 -> FALSE | F41: =COUNTIF('Duplicates_with_Master DB'!$A:$A,Sheet1!O41)>0 -> FALSE | G41: =COUNTIF('Duplicates_with_Master DB'!$A:$A,Sheet1!P41)>0 -> FALSE | H41: =COUNTIF('Duplicates_with_Master DB'!$A:$A,Sheet1!Q41)>0 -> FALSE | I41: =COUNTIF('Duplicates_with_Master DB'!$A:$A,Sheet1!R41)>0 -> FALSE | J41: =COUNTIF('Duplicates_with_Master DB'!$A:$A,Sheet1!S41)>0 -> FALSE | K41: =COUNTIF('Duplicates_with_Master DB'!$A:$A,Sheet1!T41)>0 -> FALSE | L41: =M41 & IF(COUNTA(N41:T41), ", " & _xlfn.TEXTJOIN(", ", TRUE, N41:T41), "") -> 94778699 | M41: 94778699 | U41: clarence.chan@tangteahouse.com
A42: Niveken | B42: Jo ting | D42: =COUNTIF('Duplicates_with_Master DB'!$A:$A,Sheet1!M42)>0 -> FALSE | E42: =COUNTIF('Duplicates_with_Master DB'!$A:$A,Sheet1!N42)>0 -> FALSE | F42: =COUNTIF('Duplicates_with_Master DB'!$A:$A,Sheet1!O42)>0 -> FALSE | G42: =COUNTIF('Duplicates_with_Master DB'!$A:$A,Sheet1!P42)>0 -> FALSE | H42: =COUNTIF('Duplicates_with_Master DB'!$A:$A,Sheet1!Q42)>0 -> FALSE | I42: =COUNTIF('Duplicates_with_Master DB'!$A:$A,Sheet1!R42)>0 -> FALSE | J42: =COUNTIF('Duplicates_with_Master DB'!$A:$A,Sheet1!S42)>0 -> FALSE | K42: =COUNTIF('Duplicates_with_Master DB'!$A:$A,Sheet1!T42)>0 -> FALSE | L42: =M42 & IF(COUNTA(N42:T42), ", " & _xlfn.TEXTJOIN(", ", TRUE, N42:T42), "") -> 64343826 | M42: 64343826 | U42: joting@niveken.com
A43: Breadtalk Group | B43: Natalie | D43: =COUNTIF('Duplicates_with_Master DB'!$A:$A,Sheet1!M43)>0 -> FALSE | E43: =COUNTIF('Duplicates_with_Master DB'!$A:$A,Sheet1!N43)>0 -> FALSE | F43: =COUNTIF('Duplicates_with_Master DB'!$A:$A,Sheet1!O43)>0 -> FALSE | G43: =COUNTIF('Duplicates_with_Master DB'!$A:$A,Sheet1!P43)>0 -> FALSE | H43: =COUNTIF('Duplicates_with_Master DB'!$A:$A,Sheet1!Q43)>0 -> FALSE | I43: =COUNTIF('Duplicates_with_Master DB'!$A:$A,Sheet1!R43)>0 -> FALSE | J43: =COUNTIF('Duplicates_with_Master DB'!$A:$A,Sheet1!S43)>0 -> FALSE | K43: =COUNTIF('Duplicates_with_Master DB'!$A:$A,Sheet1!T43)>0 -> FALSE | L43: =M43 & IF(COUNTA(N43:T43), ", " & _xlfn.TEXTJOIN(", ", TRUE, N43:T43), "") -> 98236667 | M43: 98236667 | U43: natalie.ng@breadtalk.com
A44: BT | B44: Eric | D44: =COUNTIF('Duplicates_with_Master DB'!$A:$A,Sheet1!M44)>0 -> FALSE | E44: =COUNTIF('Duplicates_with_Master DB'!$A:$A,Sheet1!N44)>0 -> FALSE | F44: =COUNTIF('Duplicates_with_Master DB'!$A:$A,Sheet1!O44)>0 -> FALSE | G44: =COUNTIF('Duplicates_with_Master DB'!$A:$A,Sheet1!P44)>0 -> FALSE | H44: =COUNTIF('Duplicates_with_Master DB'!$A:$A,Sheet1!Q44)>0 -> FALSE | I44: =COUNTIF('Duplicates_with_Master DB'!$A:$A,Sheet1!R44)>0 -> FALSE | J44: =COUNTIF('Duplicates_with_Master DB'!$A:$A,Sheet1!S44)>0 -> FALSE | K44: =COUNTIF('Duplicates_with_Master DB'!$A:$A,Sheet1!T44)>0 -> FALSE | L44: =M44 & IF(COUNTA(N44:T44), ", " & _xlfn.TEXTJOIN(", ", TRUE, N44:T44), "") -> 90078728 | M44: 90078728 | U44: eric.cham@breadtalk.com
A45: Baker and Cook | B45: Jenni | D45: =COUNTIF('Duplicates_with_Master DB'!$A:$A,Sheet1!M45)>0 -> FALSE | E45: =COUNTIF('Duplicates_with_Master DB'!$A:$A,Sheet1!N45)>0 -> FALSE | F45: =COUNTIF('Duplicates_with_Master DB'!$A:$A,Sheet1!O45)>0 -> FALSE | G45: =COUNTIF('Duplicates_with_Master DB'!$A:$A,Sheet1!P45)>0 -> FALSE | H45: =COUNTIF('Duplicates_with_Master DB'!$A:$A,Sheet1!Q45)>0 -> FALSE | I45: =COUNTIF('Duplicates_with_Master DB'!$A:$A,Sheet1!R45)>0 -> FALSE | J45: =COUNTIF('Duplicates_with_Master DB'!$A:$A,Sheet1!S45)>0 -> FALSE | K45: =COUNTIF('Duplicates_with_Master DB'!$A:$A,Sheet1!T45)>0 -> FALSE | L45: =M45 & IF(COUNTA(N45:T45), ", " & _xlfn.TEXTJOIN(", ", TRUE, N45:T45), "") -> 91283069 | M45: 91283069 | U45: martin.jenni@rocketmail.com
... A63: IFS capital | B63: Jia Jun | D63: =COUNTIF('Duplicates_with_Master DB'!$A:$A,Sheet1!M63)>0 -> FALSE | E63: =COUNTIF('Duplicates_with_Master DB'!$A:$A,Sheet1!N63)>0 -> FALSE | F63: =COUNTIF('Duplicates_with_Master DB'!$A:$A,Sheet1!O63)>0 -> FALSE | G63: =COUNTIF('Duplicates_with_Master DB'!$A:$A,Sheet1!P63)>0 -> FALSE | H63: =COUNTIF('Duplicates_with_Master DB'!$A:$A,Sheet1!Q63)>0 -> FALSE | I63: =COUNTIF('Duplicates_with_Master DB'!$A:$A,Sheet1!R63)>0 -> FALSE | J63: =COUNTIF('Duplicates_with_Master DB'!$A:$A,Sheet1!S63)>0 -> FALSE | K63: =COUNTIF('Duplicates_with_Master DB'!$A:$A,Sheet1!T63)>0 -> FALSE | L63: =M63 & IF(COUNTA(N63:T63), ", " & _xlfn.TEXTJOIN(", ", TRUE, N63:T63), "") -> 82883863 | M63: 82883863 | U63: jiajun.lim@ifscapital.com.sg
A64: Anonymous | B64: Sean | D64: =COUNTIF('Duplicates_with_Master DB'!$A:$A,Sheet1!M64)>0 -> FALSE | E64: =COUNTIF('Duplicates_with_Master DB'!$A:$A,Sheet1!N64)>0 -> FALSE | F64: =COUNTIF('Duplicates_with_Master DB'!$A:$A,Sheet1!O64)>0 -> FALSE | G64: =COUNTIF('Duplicates_with_Master DB'!$A:$A,Sheet1!P64)>0 -> FALSE | H64: =COUNTIF('Duplicates_with_Master DB'!$A:$A,Sheet1!Q64)>0 -> FALSE | I64: =COUNTIF('Duplicates_with_Master DB'!$A:$A,Sheet1!R64)>0 -> FALSE | J64: =COUNTIF('Duplicates_with_Master DB'!$A:$A,Sheet1!S64)>0 -> FALSE | K64: =COUNTIF('Duplicates_with_Master DB'!$A:$A,Sheet1!T64)>0 -> FALSE | L64: =M64 & IF(COUNTA(N64:T64), ", " & _xlfn.TEXTJOIN(", ", TRUE, N64:T64), "") | U64: aw.sean@gmail.com
A65: restaurant | B65: Ali Affan Khan | D65: =COUNTIF('Duplicates_with_Master DB'!$A:$A,Sheet1!M65)>0 -> FALSE | E65: =COUNTIF('Duplicates_with_Master DB'!$A:$A,Sheet1!N65)>0 -> FALSE | F65: =COUNTIF('Duplicates_with_Master DB'!$A:$A,Sheet1!O65)>0 -> FALSE | G65: =COUNTIF('Duplicates_with_Master DB'!$A:$A,Sheet1!P65)>0 -> FALSE | H65: =COUNTIF('Duplicates_with_Master DB'!$A:$A,Sheet1!Q65)>0 -> FALSE | I65: =COUNTIF('Duplicates_with_Master DB'!$A:$A,Sheet1!R65)>0 -> FALSE | J65: =COUNTIF('Duplicates_with_Master DB'!$A:$A,Sheet1!S65)>0 -> FALSE | K65: =COUNTIF('Duplicates_with_Master DB'!$A:$A,Sheet1!T65)>0 -> FALSE | L65: =M65 & IF(COUNTA(N65:T65), ", " & _xlfn.TEXTJOIN(", ", TRUE, N65:T65), "") -> 93286500 | M65: 93286500 | U65: khanaliaffan@yahoo.com
A66: HRS | B66: Raphael Fam | D66: =COUNTIF('Duplicates_with_Master DB'!$A:$A,Sheet1!M66)>0 -> FALSE | E66: =COUNTIF('Duplicates_with_Master DB'!$A:$A,Sheet1!N66)>0 -> FALSE | F66: =COUNTIF('Duplicates_with_Master DB'!$A:$A,Sheet1!O66)>0 -> FALSE | G66: =COUNTIF('Duplicates_with_Master DB'!$A:$A,Sheet1!P66)>0 -> FALSE | H66: =COUNTIF('Duplicates_with_Master DB'!$A:$A,Sheet1!Q66)>0 -> FALSE | I66: =COUNTIF('Duplicates_with_Master DB'!$A:$A,Sheet1!R66)>0 -> FALSE | J66: =COUNTIF('Duplicates_with_Master DB'!$A:$A,Sheet1!S66)>0 -> FALSE | K66: =COUNTIF('Duplicates_with_Master DB'!$A:$A,Sheet1!T66)>0 -> FALSE | L66: =M66 & IF(COUNTA(N66:T66), ", " & _xlfn.TEXTJOIN(", ", TRUE, N66:T66), "") -> 91510348 | M66: 91510348 | U66: rfam@hrsinternational.com
A67: ERA | B67: Zai | D67: =COUNTIF('Duplicates_with_Master DB'!$A:$A,Sheet1!M67)>0 -> FALSE | E67: =COUNTIF('Duplicates_with_Master DB'!$A:$A,Sheet1!N67)>0 -> FALSE | F67: =COUNTIF('Duplicates_with_Master DB'!$A:$A,Sheet1!O67)>0 -> FALSE | G67: =COUNTIF('Duplicates_with_Master DB'!$A:$A,Sheet1!P67)>0 -> FALSE | H67: =COUNTIF('Duplicates_with_Master DB'!$A:$A,Sheet1!Q67)>0 -> FALSE | I67: =COUNTIF('Duplicates_with_Master DB'!$A:$A,Sheet1!R67)>0 -> FALSE | J67: =COUNTIF('Duplicates_with_Master DB'!$A:$A,Sheet1!S67)>0 -> FALSE | K67: =COUNTIF('Duplicates_with_Master DB'!$A:$A,Sheet1!T67)>0 -> FALSE | L67: =M67 & IF(COUNTA(N67:T67), ", " & _xlfn.TEXTJOIN(", ", TRUE, N67:T67), "") -> 90909274 | M67: 90909274 | U67: zaimi3878@gmail.com
A68: Conflate | B68: Khanna | D68: =COUNTIF('Duplicates_with_Master DB'!$A:$A,Sheet1!M68)>0 -> FALSE | E68: =COUNTIF('Duplicates_with_Master DB'!$A:$A,Sheet1!N68)>0 -> FALSE | F68: =COUNTIF('Duplicates_with_Master DB'!$A:$A,Sheet1!O68)>0 -> FALSE | G68: =COUNTIF('Duplicates_with_Master DB'!$A:$A,Sheet1!P68)>0 -> FALSE | H68: =COUNTIF('Duplicates_with_Master DB'!$A:$A,Sheet1!Q68)>0 -> FALSE | I68: =COUNTIF('Duplicates_with_Master DB'!$A:$A,Sheet1!R68)>0 -> FALSE | J68: =COUNTIF('Duplicates_with_Master DB'!$A:$A,Sheet1!S68)>0 -> FALSE | K68: =COUNTIF('Duplicates_with_Master DB'!$A:$A,Sheet1!T68)>0 -> FALSE | L68: =M68 & IF(COUNTA(N68:T68), ", " & _xlfn.TEXTJOIN(", ", TRUE, N68:T68), "") -> 85249728 | M68: 85249728 | U68: conflate.sing@gmail.com
A69: Royal T Group Pte Ltd | B69: Pamela | D69: =COUNTIF('Duplicates_with_Master DB'!$A:$A,Sheet1!M69)>0 -> FALSE | E69: =COUNTIF('Duplicates_with_Master DB'!$A:$A,Sheet1!N69)>0 -> FALSE | F69: =COUNTIF('Duplicates_with_Master DB'!$A:$A,Sheet1!O69)>0 -> FALSE | G69: =COUNTIF('Duplicates_with_Master DB'!$A:$A,Sheet1!P69)>0 -> FALSE | H69: =COUNTIF('Duplicates_with_Master DB'!$A:$A,Sheet1!Q69)>0 -> FALSE | I69: =COUNTIF('Duplicates_with_Master DB'!$A:$A,Sheet1!R69)>0 -> FALSE | J69: =COUNTIF('Duplicates_with_Master DB'!$A:$A,Sheet1!S69)>0 -> FALSE | K69: =COUNTIF('Duplicates_with_Master DB'!$A:$A,Sheet1!T69)>0 -> FALSE | L69: =M69 & IF(COUNTA(N69:T69), ", " & _xlfn.TEXTJOIN(", ", TRUE, N69:T69), "") -> 92223422 | M69: 92223422 | U69: pamela.ang22@gmail.com
A70: Chilli Padi Holding Pte Ltd | B70: Rizal | D70: =COUNTIF('Duplicates_with_Master DB'!$A:$A,Sheet1!M70)>0 -> FALSE | E70: =COUNTIF('Duplicates_with_Master DB'!$A:$A,Sheet1!N70)>0 -> FALSE | F70: =COUNTIF('Duplicates_with_Master DB'!$A:$A,Sheet1!O70)>0 -> FALSE | G70: =COUNTIF('Duplicates_with_Master DB'!$A:$A,Sheet1!P70)>0 -> FALSE | H70: =COUNTIF('Duplicates_with_Master DB'!$A:$A,Sheet1!Q70)>0 -> FALSE | I70: =COUNTIF('Duplicates_with_Master DB'!$A:$A,Sheet1!R70)>0 -> FALSE | J70: =COUNTIF('Duplicates_with_Master DB'!$A:$A,Sheet1!S70)>0 -> FALSE | K70: =COUNTIF('Duplicates_with_Master DB'!$A:$A,Sheet1!T70)>0 -> FALSE | L70: =M70 & IF(COUNTA(N70:T70), ", " & _xlfn.TEXTJOIN(", ", TRUE, N70:T70), "") -> 90676090 | M70: 90676090 | U70: sharizal@chillipadi.com.sg
A71: Tan soon mui | B71: Tan | D71: =COUNTIF('Duplicates_with_Master DB'!$A:$A,Sheet1!M71)>0 -> FALSE | E71: =COUNTIF('Duplicates_with_Master DB'!$A:$A,Sheet1!N71)>0 -> FALSE | F71: =COUNTIF('Duplicates_with_Master DB'!$A:$A,Sheet1!O71)>0 -> FALSE | G71: =COUNTIF('Duplicates_with_Master DB'!$A:$A,Sheet1!P71)>0 -> FALSE | H71: =COUNTIF('Duplicates_with_Master DB'!$A:$A,Sheet1!Q71)>0 -> FALSE | I71: =COUNTIF('Duplicates_with_Master DB'!$A:$A,Sheet1!R71)>0 -> FALSE | J71: =COUNTIF('Duplicates_with_Master DB'!$A:$A,Sheet1!S71)>0 -> FALSE | K71: =COUNTIF('Duplicates_with_Master DB'!$A:$A,Sheet1!T71)>0 -> FALSE | L71: =M71 & IF(COUNTA(N71:T71), ", " & _xlfn.TEXTJOIN(", ", TRUE, N71:T71), "") -> 86868988 | M71: 86868988 | U71: ryantan988@gmail.com
A72: Ourglass | B72: William | D72: =COUNTIF('Duplicates_with_Master DB'!$A:$A,Sheet1!M72)>0 -> FALSE | E72: =COUNTIF('Duplicates_with_Master DB'!$A:$A,Sheet1!N72)>0 -> FALSE | F72: =COUNTIF('Duplicates_with_Master DB'!$A:$A,Sheet1!O72)>0 -> FALSE | G72: =COUNTIF('Duplicates_with_Master DB'!$A:$A,Sheet1!P72)>0 -> FALSE | H72: =COUNTIF('Duplicates_with_Master DB'!$A:$A,Sheet1!Q72)>0 -> FALSE | I72: =COUNTIF('Duplicates_with_Master DB'!$A:$A,Sheet1!R72)>0 -> FALSE | J72: =COUNTIF('Duplicates_with_Master DB'!$A:$A,Sheet1!S72)>0 -> FALSE | K72: =COUNTIF('Duplicates_with_Master DB'!$A:$A,Sheet1!T72)>0 -> FALSE | L72: =M72 & IF(COUNTA(N72:T72), ", " & _xlfn.TEXTJOIN(", ", TRUE, N72:T72), "") -> 83232726 | M72: 83232726 | U72: william@ourglass.sg
A73: Ddy's Kitchen | B73: Linda Rahman | D73: =COUNTIF('Duplicates_with_Master DB'!$A:$A,Sheet1!M73)>0 -> FALSE | E73: =COUNTIF('Duplicates_with_Master DB'!$A:$A,Sheet1!N73)>0 -> FALSE | F73: =COUNTIF('Duplicates_with_Master DB'!$A:$A,Sheet1!O73)>0 -> FALSE | G73: =COUNTIF('Duplicates_with_Master DB'!$A:$A,Sheet1!P73)>0 -> FALSE | H73: =COUNTIF('Duplicates_with_Master DB'!$A:$A,Sheet1!Q73)>0 -> FALSE | I73: =COUNTIF('Duplicates_with_Master DB'!$A:$A,Sheet1!R73)>0 -> FALSE | J73: =COUNTIF('Duplicates_with_Master DB'!$A:$A,Sheet1!S73)>0 -> FALSE | K73: =COUNTIF('Duplicates_with_Master DB'!$A:$A,Sheet1!T73)>0 -> FALSE | L73: =M73 & IF(COUNTA(N73:T73), ", " & _xlfn.TEXTJOIN(", ", TRUE, N73:T73), "") | U73: lyynrahman@gmail.com
A74: Coffee Malaya | B74: Johan Nasir | D74: =COUNTIF('Duplicates_with_Master DB'!$A:$A,Sheet1!M74)>0 -> FALSE | E74: =COUNTIF('Duplicates_with_Master DB'!$A:$A,Sheet1!N74)>0 -> FALSE | F74: =COUNTIF('Duplicates_with_Master DB'!$A:$A,Sheet1!O74)>0 -> FALSE | G74: =COUNTIF('Duplicates_with_Master DB'!$A:$A,Sheet1!P74)>0 -> FALSE | H74: =COUNTIF('Duplicates_with_Master DB'!$A:$A,Sheet1!Q74)>0 -> FALSE | I74: =COUNTIF('Duplicates_with_Master DB'!$A:$A,Sheet1!R74)>0 -> FALSE | J74: =COUNTIF('Duplicates_with_Master DB'!$A:$A,Sheet1!S74)>0 -> FALSE | K74: =COUNTIF('Duplicates_with_Master DB'!$A:$A,Sheet1!T74)>0 -> FALSE | L74: =M74 & IF(COUNTA(N74:T74), ", " & _xlfn.TEXTJOIN(", ", TRUE, N74:T74), "") | U74: inquiries.coffeemalaya@gmail.com
A75: 10 Points Pte Ltd | D75: =COUNTIF('Duplicates_with_Master DB'!$A:$A,Sheet1!M75)>0 -> FALSE | E75: =COUNTIF('Duplicates_with_Master DB'!$A:$A,Sheet1!N75)>0 -> FALSE | F75: =COUNTIF('Duplicates_with_Master DB'!$A:$A,Sheet1!O75)>0 -> FALSE | G75: =COUNTIF('Duplicates_with_Master DB'!$A:$A,Sheet1!P75)>0 -> FALSE | H75: =COUNTIF('Duplicates_with_Master DB'!$A:$A,Sheet1!Q75)>0 -> FALSE | I75: =COUNTIF('Duplicates_with_Master DB'!$A:$A,Sheet1!R75)>0 -> FALSE | J75: =COUNTIF('Duplicates_with_Master DB'!$A:$A,Sheet1!S75)>0 -> FALSE | K75: =COUNTIF('Duplicates_with_Master DB'!$A:$A,Sheet1!T75)>0 -> FALSE | L75: =M75 & IF(COUNTA(N75:T75), ", " & _xlfn.TEXTJOIN(", ", TRUE, N75:T75), "")
A76: Xian Ding Wei @ IMM Pte Ltd | D76: =COUNTIF('Duplicates_with_Master DB'!$A:$A,Sheet1!M76)>0 -> FALSE | E76: =COUNTIF('Duplicates_with_Master DB'!$A:$A,Sheet1!N76)>0 -> FALSE | F76: =COUNTIF('Duplicates_with_Master DB'!$A:$A,Sheet1!O76)>0 -> FALSE | G76: =COUNTIF('Duplicates_with_Master DB'!$A:$A,Sheet1!P76)>0 -> FALSE | H76: =COUNTIF('Duplicates_with_Master DB'!$A:$A,Sheet1!Q76)>0 -> FALSE | I76: =COUNTIF('Duplicates_with_Master DB'!$A:$A,Sheet1!R76)>0 -> FALSE | J76: =COUNTIF('Duplicates_with_Master DB'!$A:$A,Sheet1!S76)>0 -> FALSE | K76: =COUNTIF('Duplicates_with_Master DB'!$A:$A,Sheet1!T76)>0 -> FALSE | L76: =M76 & IF(COUNTA(N76:T76), ", " & _xlfn.TEXTJOIN(", ", TRUE, N76:T76), "") -> 97888359 | M76: 97888359 | U76: tommylh1341@gmail.com
A77: 188 Cafe pte Ltd | D77: =COUNTIF('Duplicates_with_Master DB'!$A:$A,Sheet1!M77)>0 -> FALSE | E77: =COUNTIF('Duplicates_with_Master DB'!$A:$A,Sheet1!N77)>0 -> FALSE | F77: =COUNTIF('Duplicates_with_Master DB'!$A:$A,Sheet1!O77)>0 -> FALSE | G77: =COUNTIF('Duplicates_with_Master DB'!$A:$A,Sheet1!P77)>0 -> FALSE | H77: =COUNTIF('Duplicates_with_Master DB'!$A:$A,Sheet1!Q77)>0 -> FALSE | I77: =COUNTIF('Duplicates_with_Master DB'!$A:$A,Sheet1!R77)>0 -> FALSE | J77: =COUNTIF('Duplicates_with_Master DB'!$A:$A,Sheet1!S77)>0 -> FALSE | K77: =COUNTIF('Duplicates_with_Master DB'!$A:$A,Sheet1!T77)>0 -> FALSE | L77: =M77 & IF(COUNTA(N77:T77), ", " & _xlfn.TEXTJOIN(", ", TRUE, N77:T77), "")
A78: 190 Degrees Bakery (Toa Payoh) | D78: =COUNTIF('Duplicates_with_Master DB'!$A:$A,Sheet1!M78)>0 -> FALSE | E78: =COUNTIF('Duplicates_with_Master DB'!$A:$A,Sheet1!N78)>0 -> FALSE | F78: =COUNTIF('Duplicates_with_Master DB'!$A:$A,Sheet1!O78)>0 -> FALSE | G78: =COUNTIF('Duplicates_with_Master DB'!$A:$A,Sheet1!P78)>0 -> FALSE | H78: =COUNTIF('Duplicates_with_Master DB'!$A:$A,Sheet1!Q78)>0 -> FALSE | I78: =COUNTIF('Duplicates_with_Master DB'!$A:$A,Sheet1!R78)>0 -> FALSE | J78: =COUNTIF('Duplicates_with_Master DB'!$A:$A,Sheet1!S78)>0 -> FALSE | K78: =COUNTIF('Duplicates_with_Master DB'!$A:$A,Sheet1!T78)>0 -> FALSE | L78: =M78 & IF(COUNTA(N78:T78), ", " & _xlfn.TEXTJOIN(", ", TRUE, N78:T78), "") -> 92218444 | M78: 92218444 | U78: 190degreesbakery@gmail.com
A79: 1PM Grp Pte Ltd | D79: =COUNTIF('Duplicates_with_Master DB'!$A:$A,Sheet1!M79)>0 -> FALSE | E79: =COUNTIF('Duplicates_with_Master DB'!$A:$A,Sheet1!N79)>0 -> FALSE | F79: =COUNTIF('Duplicates_with_Master DB'!$A:$A,Sheet1!O79)>0 -> FALSE | G79: =COUNTIF('Duplicates_with_Master DB'!$A:$A,Sheet1!P79)>0 -> FALSE | H79: =COUNTIF('Duplicates_with_Master DB'!$A:$A,Sheet1!Q79)>0 -> FALSE | I79: =COUNTIF('Duplicates_with_Master DB'!$A:$A,Sheet1!R79)>0 -> FALSE | J79: =COUNTIF('Duplicates_with_Master DB'!$A:$A,Sheet1!S79)>0 -> FALSE | K79: =COUNTIF('Duplicates_with_Master DB'!$A:$A,Sheet1!T79)>0 -> FALSE | L79: =M79 & IF(COUNTA(N79:T79), ", " & _xlfn.TEXTJOIN(", ", TRUE, N79:T79), "") -> 83889300 | M79: 83889300 | U79: kieranfoowx@gmail.com
A80: Nakama Ramen | D80: =COUNTIF('Duplicates_with_Master DB'!$A:$A,Sheet1!M80)>0 -> FALSE | E80: =COUNTIF('Duplicates_with_Master DB'!$A:$A,Sheet1!N80)>0 -> FALSE | F80: =COUNTIF('Duplicates_with_Master DB'!$A:$A,Sheet1!O80)>0 -> FALSE | G80: =COUNTIF('Duplicates_with_Master DB'!$A:$A,Sheet1!P80)>0 -> FALSE | H80: =COUNTIF('Duplicates_with_Master DB'!$A:$A,Sheet1!Q80)>0 -> FALSE | I80: =COUNTIF('Duplicates_with_Master DB'!$A:$A,Sheet1!R80)>0 -> FALSE | J80: =COUNTIF('Duplicates_with_Master DB'!$A:$A,Sheet1!S80)>0 -> FALSE | K80: =COUNTIF('Duplicates_with_Master DB'!$A:$A,Sheet1!T80)>0 -> FALSE | L80: =M80 & IF(COUNTA(N80:T80), ", " & _xlfn.TEXTJOIN(", ", TRUE, N80:T80), "") -> 83889300 | M80: 83889300 | U80: kieranfoowx@gmail.com
A81: 200 HCM Food Pte Ltd | D81: =COUNTIF('Duplicates_with_Master DB'!$A:$A,Sheet1!M81)>0 -> FALSE | E81: =COUNTIF('Duplicates_with_Master DB'!$A:$A,Sheet1!N81)>0 -> FALSE | F81: =COUNTIF('Duplicates_with_Master DB'!$A:$A,Sheet1!O81)>0 -> FALSE | G81: =COUNTIF('Duplicates_with_Master DB'!$A:$A,Sheet1!P81)>0 -> FALSE | H81: =COUNTIF('Duplicates_with_Master DB'!$A:$A,Sheet1!Q81)>0 -> FALSE | I81: =COUNTIF('Duplicates_with_Master DB'!$A:$A,Sheet1!R81)>0 -> FALSE | J81: =COUNTIF('Duplicates_with_Master DB'!$A:$A,Sheet1!S81)>0 -> FALSE | K81: =COUNTIF('Duplicates_with_Master DB'!$A:$A,Sheet1!T81)>0 -> FALSE | L81: =M81 & IF(COUNTA(N81:T81), ", " & _xlfn.TEXTJOIN(", ", TRUE, N81:T81), "") -> 82636363 | M81: 82636363 | U81: rambo.song@yahoo.com
A82: 2Degrees North Coffee Co. Pte Ltd | D82: =COUNTIF('Duplicates_with_Master DB'!$A:$A,Sheet1!M82)>0 -> FALSE | E82: =COUNTIF('Duplicates_with_Master DB'!$A:$A,Sheet1!N82)>0 -> FALSE | F82: =COUNTIF('Duplicates_with_Master DB'!$A:$A,Sheet1!O82)>0 -> FALSE | G82: =COUNTIF('Duplicates_with_Master DB'!$A:$A,Sheet1!P82)>0 -> FALSE | H82: =COUNTIF('Duplicates_with_Master DB'!$A:$A,Sheet1!Q82)>0 -> FALSE | I82: =COUNTIF('Duplicates_with_Master DB'!$A:$A,Sheet1!R82)>0 -> FALSE | J82: =COUNTIF('Duplicates_with_Master DB'!$A:$A,Sheet1!S82)>0 -> FALSE | K82: =COUNTIF('Duplicates_with_Master DB'!$A:$A,Sheet1!T82)>0 -> FALSE | L82: =M82 & IF(COUNTA(N82:T82), ", " & _xlfn.TEXTJOIN(", ", TRUE, N82:T82), "") -> 97634200 | M82: 97634200 | U82: kyy1992@gmail.com
A83: The Populus Coffee & Food Co. | D83: =COUNTIF('Duplicates_with_Master DB'!$A:$A,Sheet1!M83)>0 -> FALSE | E83: =COUNTIF('Duplicates_with_Master DB'!$A:$A,Sheet1!N83)>0 -> FALSE | F83: =COUNTIF('Duplicates_with_Master DB'!$A:$A,Sheet1!O83)>0 -> FALSE | G83: =COUNTIF('Duplicates_with_Master DB'!$A:$A,Sheet1!P83)>0 -> FALSE | H83: =COUNTIF('Duplicates_with_Master DB'!$A:$A,Sheet1!Q83)>0 -> FALSE | I83: =COUNTIF('Duplicates_with_Master DB'!$A:$A,Sheet1!R83)>0 -> FALSE | J83: =COUNTIF('Duplicates_with_Master DB'!$A:$A,Sheet1!S83)>0 -> FALSE | K83: =COUNTIF('Duplicates_with_Master DB'!$A:$A,Sheet1!T83)>0 -> FALSE | L83: =M83 & IF(COUNTA(N83:T83), ", " & _xlfn.TEXTJOIN(", ", TRUE, N83:T83), "") -> 97634200 | M83: 97634200 | U83: kyy1992@gmail.com
A84: 2Six Pte Ltd | D84: =COUNTIF('Duplicates_with_Master DB'!$A:$A,Sheet1!M84)>0 -> FALSE | E84: =COUNTIF('Duplicates_with_Master DB'!$A:$A,Sheet1!N84)>0 -> FALSE | F84: =COUNTIF('Duplicates_with_Master DB'!$A:$A,Sheet1!O84)>0 -> FALSE | G84: =COUNTIF('Duplicates_with_Master DB'!$A:$A,Sheet1!P84)>0 -> FALSE | H84: =COUNTIF('Duplicates_with_Master DB'!$A:$A,Sheet1!Q84)>0 -> FALSE | I84: =COUNTIF('Duplicates_with_Master DB'!$A:$A,Sheet1!R84)>0 -> FALSE | J84: =COUNTIF('Duplicates_with_Master DB'!$A:$A,Sheet1!S84)>0 -> FALSE | K84: =COUNTIF('Duplicates_with_Master DB'!$A:$A,Sheet1!T84)>0 -> FALSE | L84: =M84 & IF(COUNTA(N84:T84), ", " & _xlfn.TEXTJOIN(", ", TRUE, N84:T84), "") -> 97611606 | M84: 97611606 | U84: enquiry@2six.com.sg
D85: =COUNTIF('Duplicates_with_Master DB'!$A:$A,Sheet1!M85)>0 -> FALSE | E85: =COUNTIF('Duplicates_with_Master DB'!$A:$A,Sheet1!N85)>0 -> FALSE | F85: =COUNTIF('Duplicates_with_Master DB'!$A:$A,Sheet1!O85)>0 -> FALSE | G85: =COUNTIF('Duplicates_with_Master DB'!$A:$A,Sheet1!P85)>0 -> FALSE | H85: =COUNTIF('Duplicates_with_Master DB'!$A:$A,Sheet1!Q85)>0 -> FALSE | I85: =COUNTIF('Duplicates_with_Master DB'!$A:$A,Sheet1!R85)>0 -> FALSE | J85: =COUNTIF('Duplicates_with_Master DB'!$A:$A,Sheet1!S85)>0 -> FALSE | K85: =COUNTIF('Duplicates_with_Master DB'!$A:$A,Sheet1!T85)>0 -> FALSE | L85: =M85 & IF(COUNTA(N85:T85), ", " & _xlfn.TEXTJOIN(", ", TRUE, N85:T85), "")
A86: 4Fingers Singapore Pte Ltd | D86: =COUNTIF('Duplicates_with_Master DB'!$A:$A,Sheet1!M86)>0 -> FALSE | E86: =COUNTIF('Duplicates_with_Master DB'!$A:$A,Sheet1!N86)>0 -> FALSE | F86: =COUNTIF('Duplicates_with_Master DB'!$A:$A,Sheet1!O86)>0 -> FALSE | G86: =COUNTIF('Duplicates_with_Master DB'!$A:$A,Sheet1!P86)>0 -> FALSE | H86: =COUNTIF('Duplicates_with_Master DB'!$A:$A,Sheet1!Q86)>0 -> FALSE | I86: =COUNTIF('Duplicates_with_Master DB'!$A:$A,Sheet1!R86)>0 -> FALSE | J86: =COUNTIF('Duplicates_with_Master DB'!$A:$A,Sheet1!S86)>0 -> FALSE | K86: =COUNTIF('Duplicates_with_Master DB'!$A:$A,Sheet1!T86)>0 -> FALSE | L86: =M86 & IF(COUNTA(N86:T86), ", " & _xlfn.TEXTJOIN(", ", TRUE, N86:T86), "") | U86: itsupport@4fingers.com, charis@4fingers.com, ivan.chhua@4fingers.com,finance@4fingers.com
D87: =COUNTIF('Duplicates_with_Master DB'!$A:$A,Sheet1!M87)>0 -> FALSE | E87: =COUNTIF('Duplicates_with_Master DB'!$A:$A,Sheet1!N87)>0 -> FALSE | F87: =COUNTIF('Duplicates_with_Master DB'!$A:$A,Sheet1!O87)>0 -> FALSE | G87: =COUNTIF('Duplicates_with_Master DB'!$A:$A,Sheet1!P87)>0 -> FALSE | H87: =COUNTIF('Duplicates_with_Master DB'!$A:$A,Sheet1!Q87)>0 -> FALSE | I87: =COUNTIF('Duplicates_with_Master DB'!$A:$A,Sheet1!R87)>0 -> FALSE | J87: =COUNTIF('Duplicates_with_Master DB'!$A:$A,Sheet1!S87)>0 -> FALSE | K87: =COUNTIF('Duplicates_with_Master DB'!$A:$A,Sheet1!T87)>0 -> FALSE | L87: =M87 & IF(COUNTA(N87:T87), ", " & _xlfn.TEXTJOIN(", ", TRUE, N87:T87), "") | U87: itsupport@4fingers.com, charis@4fingers.com, ivan.chhua@4fingers.com,finance@4fingers.com
A88: 4Fingers @ White Sands Mall | D88: =COUNTIF('Duplicates_with_Master DB'!$A:$A,Sheet1!M88)>0 -> FALSE | E88: =COUNTIF('Duplicates_with_Master DB'!$A:$A,Sheet1!N88)>0 -> FALSE | F88: =COUNTIF('Duplicates_with_Master DB'!$A:$A,Sheet1!O88)>0 -> FALSE | G88: =COUNTIF('Duplicates_with_Master DB'!$A:$A,Sheet1!P88)>0 -> FALSE | H88: =COUNTIF('Duplicates_with_Master DB'!$A:$A,Sheet1!Q88)>0 -> FALSE | I88: =COUNTIF('Duplicates_with_Master DB'!$A:$A,Sheet1!R88)>0 -> FALSE | J88: =COUNTIF('Duplicates_with_Master DB'!$A:$A,Sheet1!S88)>0 -> FALSE | K88: =COUNTIF('Duplicates_with_Master DB'!$A:$A,Sheet1!T88)>0 -> FALSE | L88: =M88 & IF(COUNTA(N88:T88), ", " & _xlfn.TEXTJOIN(", ", TRUE, N88:T88), "") | U88: itsupport@4fingers.com, charis@4fingers.com, ivan.chhua@4fingers.com,finance@4fingers.com
A89: 6ix 6ix Restaurant and Bar Pte Ltd | D89: =COUNTIF('Duplicates_with_Master DB'!$A:$A,Sheet1!M89)>0 -> FALSE | E89: =COUNTIF('Duplicates_with_Master DB'!$A:$A,Sheet1!N89)>0 -> FALSE | F89: =COUNTIF('Duplicates_with_Master DB'!$A:$A,Sheet1!O89)>0 -> FALSE | G89: =COUNTIF('Duplicates_with_Master DB'!$A:$A,Sheet1!P89)>0 -> FALSE | H89: =COUNTIF('Duplicates_with_Master DB'!$A:$A,Sheet1!Q89)>0 -> FALSE | I89: =COUNTIF('Duplicates_with_Master DB'!$A:$A,Sheet1!R89)>0 -> FALSE | J89: =COUNTIF('Duplicates_with_Master DB'!$A:$A,Sheet1!S89)>0 -> FALSE | K89: =COUNTIF('Duplicates_with_Master DB'!$A:$A,Sheet1!T89)>0 -> FALSE | L89: =M89 & IF(COUNTA(N89:T89), ", " & _xlfn.TEXTJOIN(", ", TRUE, N89:T89), "") -> 90881121 | M89: 90881121 | U89: Wendy@6ix6ix.com.sg
A90: 6ix 6ix (六六) | D90: =COUNTIF('Duplicates_with_Master DB'!$A:$A,Sheet1!M90)>0 -> FALSE | E90: =COUNTIF('Duplicates_with_Master DB'!$A:$A,Sheet1!N90)>0 -> FALSE | F90: =COUNTIF('Duplicates_with_Master DB'!$A:$A,Sheet1!O90)>0 -> FALSE | G90: =COUNTIF('Duplicates_with_Master DB'!$A:$A,Sheet1!P90)>0 -> FALSE | H90: =COUNTIF('Duplicates_with_Master DB'!$A:$A,Sheet1!Q90)>0 -> FALSE | I90: =COUNTIF('Duplicates_with_Master DB'!$A:$A,Sheet1!R90)>0 -> FALSE | J90: =COUNTIF('Duplicates_with_Master DB'!$A:$A,Sheet1!S90)>0 -> FALSE | K90: =COUNTIF('Duplicates_with_Master DB'!$A:$A,Sheet1!T90)>0 -> FALSE | L90: =M90 & IF(COUNTA(N90:T90), ", " & _xlfn.TEXTJOIN(", ", TRUE, N90:T90), "") -> 90881121 | M90: 90881121 | U90: Wendy@6ix6ix.com.sg
A91: 7 Inch Square Pizza Pte Ltd | D91: =COUNTIF('Duplicates_with_Master DB'!$A:$A,Sheet1!M91)>0 -> FALSE | E91: =COUNTIF('Duplicates_with_Master DB'!$A:$A,Sheet1!N91)>0 -> FALSE | F91: =COUNTIF('Duplicates_with_Master DB'!$A:$A,Sheet1!O91)>0 -> FALSE | G91: =COUNTIF('Duplicates_with_Master DB'!$A:$A,Sheet1!P91)>0 -> FALSE | H91: =COUNTIF('Duplicates_with_Master DB'!$A:$A,Sheet1!Q91)>0 -> FALSE | I91: =COUNTIF('Duplicates_with_Master DB'!$A:$A,Sheet1!R91)>0 -> FALSE | J91: =COUNTIF('Duplicates_with_Master DB'!$A:$A,Sheet1!S91)>0 -> FALSE | K91: =COUNTIF('Duplicates_with_Master DB'!$A:$A,Sheet1!T91)>0 -> FALSE | L91: =M91 & IF(COUNTA(N91:T91), ", " & _xlfn.TEXTJOIN(", ", TRUE, N91:T91), "") -> 90258148 | M91: 90258148 | U91: kokjinhui89@gmail.com
A92: Pasta Express | D92: =COUNTIF('Duplicates_with_Master DB'!$A:$A,Sheet1!M92)>0 -> FALSE | E92: =COUNTIF('Duplicates_with_Master DB'!$A:$A,Sheet1!N92)>0 -> FALSE | F92: =COUNTIF('Duplicates_with_Master DB'!$A:$A,Sheet1!O92)>0 -> FALSE | G92: =COUNTIF('Duplicates_with_Master DB'!$A:$A,Sheet1!P92)>0 -> FALSE | H92: =COUNTIF('Duplicates_with_Master DB'!$A:$A,Sheet1!Q92)>0 -> FALSE | I92: =COUNTIF('Duplicates_with_Master DB'!$A:$A,Sheet1!R92)>0 -> FALSE | J92: =COUNTIF('Duplicates_with_Master DB'!$A:$A,Sheet1!S92)>0 -> FALSE | K92: =COUNTIF('Duplicates_with_Master DB'!$A:$A,Sheet1!T92)>0 -> FALSE | L92: =M92 & IF(COUNTA(N92:T92), ", " & _xlfn.TEXTJOIN(", ", TRUE, N92:T92), "") -> 90258148 | M92: 90258148 | U92: kokjinhui89@gmail.com
A93: 70's@RVM Pte Ltd | D93: =COUNTIF('Duplicates_with_Master DB'!$A:$A,Sheet1!M93)>0 -> FALSE | E93: =COUNTIF('Duplicates_with_Master DB'!$A:$A,Sheet1!N93)>0 -> FALSE | F93: =COUNTIF('Duplicates_with_Master DB'!$A:$A,Sheet1!O93)>0 -> FALSE | G93: =COUNTIF('Duplicates_with_Master DB'!$A:$A,Sheet1!P93)>0 -> FALSE | H93: =COUNTIF('Duplicates_with_Master DB'!$A:$A,Sheet1!Q93)>0 -> FALSE | I93: =COUNTIF('Duplicates_with_Master DB'!$A:$A,Sheet1!R93)>0 -> FALSE | J93: =COUNTIF('Duplicates_with_Master DB'!$A:$A,Sheet1!S93)>0 -> FALSE | K93: =COUNTIF('Duplicates_with_Master DB'!$A:$A,Sheet1!T93)>0 -> FALSE | L93: =M93 & IF(COUNTA(N93:T93), ", " & _xlfn.TEXTJOIN(", ", TRUE, N93:T93), "")
A94: WTF/B LLP | D94: =COUNTIF('Duplicates_with_Master DB'!$A:$A,Sheet1!M94)>0 -> FALSE | E94: =COUNTIF('Duplicates_with_Master DB'!$A:$A,Sheet1!N94)>0 -> FALSE | F94: =COUNTIF('Duplicates_with_Master DB'!$A:$A,Sheet1!O94)>0 -> FALSE | G94: =COUNTIF('Duplicates_with_Master DB'!$A:$A,Sheet1!P94)>0 -> FALSE | H94: =COUNTIF('Duplicates_with_Master DB'!$A:$A,Sheet1!Q94)>0 -> FALSE | I94: =COUNTIF('Duplicates_with_Master DB'!$A:$A,Sheet1!R94)>0 -> FALSE | J94: =COUNTIF('Duplicates_with_Master DB'!$A:$A,Sheet1!S94)>0 -> FALSE | K94: =COUNTIF('Duplicates_with_Master DB'!$A:$A,Sheet1!T94)>0 -> FALSE | L94: =M94 & IF(COUNTA(N94:T94), ", " & _xlfn.TEXTJOIN(", ", TRUE, N94:T94), "") -> 92224953 | M94: 92224953 | U94: 9sqorchard@gmail.com
A95: A Little Cakeshoppe | D95: =COUNTIF('Duplicates_with_Master DB'!$A:$A,Sheet1!M95)>0 -> FALSE | E95: =COUNTIF('Duplicates_with_Master DB'!$A:$A,Sheet1!N95)>0 -> FALSE | F95: =COUNTIF('Duplicates_with_Master DB'!$A:$A,Sheet1!O95)>0 -> FALSE | G95: =COUNTIF('Duplicates_with_Master DB'!$A:$A,Sheet1!P95)>0 -> FALSE | H95: =COUNTIF('Duplicates_with_Master DB'!$A:$A,Sheet1!Q95)>0 -> FALSE | I95: =COUNTIF('Duplicates_with_Master DB'!$A:$A,Sheet1!R95)>0 -> FALSE | J95: =COUNTIF('Duplicates_with_Master DB'!$A:$A,Sheet1!S95)>0 -> FALSE | K95: =COUNTIF('Duplicates_with_Master DB'!$A:$A,Sheet1!T95)>0 -> FALSE | L95: =M95 & IF(COUNTA(N95:T95), ", " & _xlfn.TEXTJOIN(", ", TRUE, N95:T95), "") -> 96879122 | M95: 96879122 | U95: info@alittlecakeshoppe.com
A96: A Matter of Taste Pte Ltd | D96: =COUNTIF('Duplicates_with_Master DB'!$A:$A,Sheet1!M96)>0 -> FALSE | E96: =COUNTIF('Duplicates_with_Master DB'!$A:$A,Sheet1!N96)>0 -> FALSE | F96: =COUNTIF('Duplicates_with_Master DB'!$A:$A,Sheet1!O96)>0 -> FALSE | G96: =COUNTIF('Duplicates_with_Master DB'!$A:$A,Sheet1!P96)>0 -> FALSE | H96: =COUNTIF('Duplicates_with_Master DB'!$A:$A,Sheet1!Q96)>0 -> FALSE | I96: =COUNTIF('Duplicates_with_Master DB'!$A:$A,Sheet1!R96)>0 -> FALSE | J96: =COUNTIF('Duplicates_with_Master DB'!$A:$A,Sheet1!S96)>0 -> FALSE | K96: =COUNTIF('Duplicates_with_Master DB'!$A:$A,Sheet1!T96)>0 -> FALSE | L96: =M96 & IF(COUNTA(N96:T96), ", " & _xlfn.TEXTJOIN(", ", TRUE, N96:T96), "") -> 92283559 | M96: 92283559 | U96: Ming@bbbs.com.sg
A97: Bar Bar Black Sheep- RQ | D97: =COUNTIF('Duplicates_with_Master DB'!$A:$A,Sheet1!M97)>0 -> FALSE | E97: =COUNTIF('Duplicates_with_Master DB'!$A:$A,Sheet1!N97)>0 -> FALSE | F97: =COUNTIF('Duplicates_with_Master DB'!$A:$A,Sheet1!O97)>0 -> FALSE | G97: =COUNTIF('Duplicates_with_Master DB'!$A:$A,Sheet1!P97)>0 -> FALSE | H97: =COUNTIF('Duplicates_with_Master DB'!$A:$A,Sheet1!Q97)>0 -> FALSE | I97: =COUNTIF('Duplicates_with_Master DB'!$A:$A,Sheet1!R97)>0 -> FALSE | J97: =COUNTIF('Duplicates_with_Master DB'!$A:$A,Sheet1!S97)>0 -> FALSE | K97: =COUNTIF('Duplicates_with_Master DB'!$A:$A,Sheet1!T97)>0 -> FALSE | L97: =M97 & IF(COUNTA(N97:T97), ", " & _xlfn.TEXTJOIN(", ", TRUE, N97:T97), "") -> 92283559 | M97: 92283559 | U97: Ming@bbbs.com.sg, antonio@hrsmarketing.com
D98: =COUNTIF('Duplicates_with_Master DB'!$A:$A,Sheet1!M98)>0 -> FALSE | E98: =COUNTIF('Duplicates_with_Master DB'!$A:$A,Sheet1!N98)>0 -> FALSE | F98: =COUNTIF('Duplicates_with_Master DB'!$A:$A,Sheet1!O98)>0 -> FALSE | G98: =COUNTIF('Duplicates_with_Master DB'!$A:$A,Sheet1!P98)>0 -> FALSE | H98: =COUNTIF('Duplicates_with_Master DB'!$A:$A,Sheet1!Q98)>0 -> FALSE | I98: =COUNTIF('Duplicates_with_Master DB'!$A:$A,Sheet1!R98)>0 -> FALSE | J98: =COUNTIF('Duplicates_with_Master DB'!$A:$A,Sheet1!S98)>0 -> FALSE | K98: =COUNTIF('Duplicates_with_Master DB'!$A:$A,Sheet1!T98)>0 -> FALSE | L98: =M98 & IF(COUNTA(N98:T98), ", " & _xlfn.TEXTJOIN(", ", TRUE, N98:T98), "") | U98: sergio.buttice@sg.abb.com
D99: =COUNTIF('Duplicates_with_Master DB'!$A:$A,Sheet1!M99)>0 -> FALSE | E99: =COUNTIF('Duplicates_with_Master DB'!$A:$A,Sheet1!N99)>0 -> FALSE | F99: =COUNTIF('Duplicates_with_Master DB'!$A:$A,Sheet1!O99)>0 -> FALSE | G99: =COUNTIF('Duplicates_with_Master DB'!$A:$A,Sheet1!P99)>0 -> FALSE | H99: =COUNTIF('Duplicates_with_Master DB'!$A:$A,Sheet1!Q99)>0 -> FALSE | I99: =COUNTIF('Duplicates_with_Master DB'!$A:$A,Sheet1!R99)>0 -> FALSE | J99: =COUNTIF('Duplicates_with_Master DB'!$A:$A,Sheet1!S99)>0 -> FALSE | K99: =COUNTIF('Duplicates_with_Master DB'!$A:$A,Sheet1!T99)>0 -> FALSE | L99: =M99 & IF(COUNTA(N99:T99), ", " & _xlfn.TEXTJOIN(", ", TRUE, N99:T99), "") | U99: sergio.buttice@sg.abb.com
D100: =COUNTIF('Duplicates_with_Master DB'!$A:$A,Sheet1!M100)>0 -> FALSE | E100: =COUNTIF('Duplicates_with_Master DB'!$A:$A,Sheet1!N100)>0 -> FALSE | F100: =COUNTIF('Duplicates_with_Master DB'!$A:$A,Sheet1!O100)>0 -> FALSE | G100: =COUNTIF('Duplicates_with_Master DB'!$A:$A,Sheet1!P100)>0 -> FALSE | H100: =COUNTIF('Duplicates_with_Master DB'!$A:$A,Sheet1!Q100)>0 -> FALSE | I100: =COUNTIF('Duplicates_with_Master DB'!$A:$A,Sheet1!R100)>0 -> FALSE | J100: =COUNTIF('Duplicates_with_Master DB'!$A:$A,Sheet1!S100)>0 -> FALSE | K100: =COUNTIF('Duplicates_with_Master DB'!$A:$A,Sheet1!T100)>0 -> FALSE | L100: =M100 & IF(COUNTA(N100:T100), ", " & _xlfn.TEXTJOIN(", ", TRUE, N100:T100), "")
D101: =COUNTIF('Duplicates_with_Master DB'!$A:$A,Sheet1!M101)>0 -> FALSE | E101: =COUNTIF('Duplicates_with_Master DB'!$A:$A,Sheet1!N101)>0 -> FALSE | F101: =COUNTIF('Duplicates_with_Master DB'!$A:$A,Sheet1!O101)>0 -> FALSE | G101: =COUNTIF('Duplicates_with_Master DB'!$A:$A,Sheet1!P101)>0 -> FALSE | H101: =COUNTIF('Duplicates_with_Master DB'!$A:$A,Sheet1!Q101)>0 -> FALSE | I101: =COUNTIF('Duplicates_with_Master DB'!$A:$A,Sheet1!R101)>0 -> FALSE | J101: =COUNTIF('Duplicates_with_Master DB'!$A:$A,Sheet1!S101)>0 -> FALSE | K101: =COUNTIF('Duplicates_with_Master DB'!$A:$A,Sheet1!T101)>0 -> FALSE | L101: =M101 & IF(COUNTA(N101:T101), ", " & _xlfn.TEXTJOIN(", ", TRUE, N101:T101), "") | U101: 768034286@qq.com
A102: A-One F&B Group Pte Ltd | D102: =COUNTIF('Duplicates_with_Master DB'!$A:$A,Sheet1!M102)>0 -> FALSE | E102: =COUNTIF('Duplicates_with_Master DB'!$A:$A,Sheet1!N102)>0 -> FALSE | F102: =COUNTIF('Duplicates_with_Master DB'!$A:$A,Sheet1!O102)>0 -> FALSE | G102: =COUNTIF('Duplicates_with_Master DB'!$A:$A,Sheet1!P102)>0 -> FALSE | H102: =COUNTIF('Duplicates_with_Master DB'!$A:$A,Sheet1!Q102)>0 -> FALSE | I102: =COUNTIF('Duplicates_with_Master DB'!$A:$A,Sheet1!R102)>0 -> FALSE | J102: =COUNTIF('Duplicates_with_Master DB'!$A:$A,Sheet1!S102)>0 -> FALSE | K102: =COUNTIF('Duplicates_with_Master DB'!$A:$A,Sheet1!T102)>0 -> FALSE | L102: =M102 & IF(COUNTA(N102:T102), ", " & _xlfn.TEXTJOIN(", ", TRUE, N102:T102), "") -> 97823733 | M102: 97823733 | U102: lucas.ter@aonegroup.sg, accounts.tabsquare@aonegroup.sg
A103: A- One Kallang Wave Mall | D103: =COUNTIF('Duplicates_with_Master DB'!$A:$A,Sheet1!M103)>0 -> FALSE | E103: =COUNTIF('Duplicates_with_Master DB'!$A:$A,Sheet1!N103)>0 -> FALSE | F103: =COUNTIF('Duplicates_with_Master DB'!$A:$A,Sheet1!O103)>0 -> FALSE | G103: =COUNTIF('Duplicates_with_Master DB'!$A:$A,Sheet1!P103)>0 -> FALSE | H103: =COUNTIF('Duplicates_with_Master DB'!$A:$A,Sheet1!Q103)>0 -> FALSE | I103: =COUNTIF('Duplicates_with_Master DB'!$A:$A,Sheet1!R103)>0 -> FALSE | J103: =COUNTIF('Duplicates_with_Master DB'!$A:$A,Sheet1!S103)>0 -> FALSE | K103: =COUNTIF('Duplicates_with_Master DB'!$A:$A,Sheet1!T103)>0 -> FALSE | L103: =M103 & IF(COUNTA(N103:T103), ", " & _xlfn.TEXTJOIN(", ", TRUE, N103:T103), "") -> 97823733 | M103: 97823733 | U103: lucas.ter@aonegroup.sg
A104: A-One Claypot House | D104: =COUNTIF('Duplicates_with_Master DB'!$A:$A,Sheet1!M104)>0 -> FALSE | E104: =COUNTIF('Duplicates_with_Master DB'!$A:$A,Sheet1!N104)>0 -> FALSE | F104: =COUNTIF('Duplicates_with_Master DB'!$A:$A,Sheet1!O104)>0 -> FALSE | G104: =COUNTIF('Duplicates_with_Master DB'!$A:$A,Sheet1!P104)>0 -> FALSE | H104: =COUNTIF('Duplicates_with_Master DB'!$A:$A,Sheet1!Q104)>0 -> FALSE | I104: =COUNTIF('Duplicates_with_Master DB'!$A:$A,Sheet1!R104)>0 -> FALSE | J104: =COUNTIF('Duplicates_with_Master DB'!$A:$A,Sheet1!S104)>0 -> FALSE | K104: =COUNTIF('Duplicates_with_Master DB'!$A:$A,Sheet1!T104)>0 -> FALSE | L104: =M104 & IF(COUNTA(N104:T104), ", " & _xlfn.TEXTJOIN(", ", TRUE, N104:T104), "") -> 97823733 | M104: 97823733 | U104: lucas.ter@aonegroup.sg
A105: A-One Junction 8 | D105: =COUNTIF('Duplicates_with_Master DB'!$A:$A,Sheet1!M105)>0 -> FALSE | E105: =COUNTIF('Duplicates_with_Master DB'!$A:$A,Sheet1!N105)>0 -> FALSE | F105: =COUNTIF('Duplicates_with_Master DB'!$A:$A,Sheet1!O105)>0 -> FALSE | G105: =COUNTIF('Duplicates_with_Master DB'!$A:$A,Sheet1!P105)>0 -> FALSE | H105: =COUNTIF('Duplicates_with_Master DB'!$A:$A,Sheet1!Q105)>0 -> FALSE | I105: =COUNTIF('Duplicates_with_Master DB'!$A:$A,Sheet1!R105)>0 -> FALSE | J105: =COUNTIF('Duplicates_with_Master DB'!$A:$A,Sheet1!S105)>0 -> FALSE | K105: =COUNTIF('Duplicates_with_Master DB'!$A:$A,Sheet1!T105)>0 -> FALSE | L105: =M105 & IF(COUNTA(N105:T105), ", " & _xlfn.TEXTJOIN(", ", TRUE, N105:T105), "") -> 97823733 | M105: 97823733 | U105: lucas.ter@aonegroup.sg
A106: A-One Northpoint City | D106: =COUNTIF('Duplicates_with_Master DB'!$A:$A,Sheet1!M106)>0 -> FALSE | E106: =COUNTIF('Duplicates_with_Master DB'!$A:$A,Sheet1!N106)>0 -> FALSE | F106: =COUNTIF('Duplicates_with_Master DB'!$A:$A,Sheet1!O106)>0 -> FALSE | G106: =COUNTIF('Duplicates_with_Master DB'!$A:$A,Sheet1!P106)>0 -> FALSE | H106: =COUNTIF('Duplicates_with_Master DB'!$A:$A,Sheet1!Q106)>0 -> FALSE | I106: =COUNTIF('Duplicates_with_Master DB'!$A:$A,Sheet1!R106)>0 -> FALSE | J106: =COUNTIF('Duplicates_with_Master DB'!$A:$A,Sheet1!S106)>0 -> FALSE | K106: =COUNTIF('Duplicates_with_Master DB'!$A:$A,Sheet1!T106)>0 -> FALSE | L106: =M106 & IF(COUNTA(N106:T106), ", " & _xlfn.TEXTJOIN(", ", TRUE, N106:T106), "") -> 97823733 | M106: 97823733 | U106: lucas.ter@aonegroup.sg
A107: A-One Raffles City | D107: =COUNTIF('Duplicates_with_Master DB'!$A:$A,Sheet1!M107)>0 -> FALSE | E107: =COUNTIF('Duplicates_with_Master DB'!$A:$A,Sheet1!N107)>0 -> FALSE | F107: =COUNTIF('Duplicates_with_Master DB'!$A:$A,Sheet1!O107)>0 -> FALSE | G107: =COUNTIF('Duplicates_with_Master DB'!$A:$A,Sheet1!P107)>0 -> FALSE | H107: =COUNTIF('Duplicates_with_Master DB'!$A:$A,Sheet1!Q107)>0 -> FALSE | I107: =COUNTIF('Duplicates_with_Master DB'!$A:$A,Sheet1!R107)>0 -> FALSE | J107: =COUNTIF('Duplicates_with_Master DB'!$A:$A,Sheet1!S107)>0 -> FALSE | K107: =COUNTIF('Duplicates_with_Master DB'!$A:$A,Sheet1!T107)>0 -> FALSE | L107: =M107 & IF(COUNTA(N107:T107), ", " & _xlfn.TEXTJOIN(", ", TRUE, N107:T107), "") -> 97823733 | M107: 97823733 | U107: lucas.ter@aonegroup.sg
A108: A-One Signature @ Nex | D108: =COUNTIF('Duplicates_with_Master DB'!$A:$A,Sheet1!M108)>0 -> FALSE | E108: =COUNTIF('Duplicates_with_Master DB'!$A:$A,Sheet1!N108)>0 -> FALSE | F108: =COUNTIF('Duplicates_with_Master DB'!$A:$A,Sheet1!O108)>0 -> FALSE | G108: =COUNTIF('Duplicates_with_Master DB'!$A:$A,Sheet1!P108)>0 -> FALSE | H108: =COUNTIF('Duplicates_with_Master DB'!$A:$A,Sheet1!Q108)>0 -> FALSE | I108: =COUNTIF('Duplicates_with_Master DB'!$A:$A,Sheet1!R108)>0 -> FALSE | J108: =COUNTIF('Duplicates_with_Master DB'!$A:$A,Sheet1!S108)>0 -> FALSE | K108: =COUNTIF('Duplicates_with_Master DB'!$A:$A,Sheet1!T108)>0 -> FALSE | L108: =M108 & IF(COUNTA(N108:T108), ", " & _xlfn.TEXTJOIN(", ", TRUE, N108:T108), "") -> 97823733 | M108: 97823733 | U108: lucas.ter@aonegroup.sg, accounts.tabsquare@aonegroup.sg
A109: A-One Signature Causeway Point | D109: =COUNTIF('Duplicates_with_Master DB'!$A:$A,Sheet1!M109)>0 -> FALSE | E109: =COUNTIF('Duplicates_with_Master DB'!$A:$A,Sheet1!N109)>0 -> FALSE | F109: =COUNTIF('Duplicates_with_Master DB'!$A:$A,Sheet1!O109)>0 -> FALSE | G109: =COUNTIF('Duplicates_with_Master DB'!$A:$A,Sheet1!P109)>0 -> FALSE | H109: =COUNTIF('Duplicates_with_Master DB'!$A:$A,Sheet1!Q109)>0 -> FALSE | I109: =COUNTIF('Duplicates_with_Master DB'!$A:$A,Sheet1!R109)>0 -> FALSE | J109: =COUNTIF('Duplicates_with_Master DB'!$A:$A,Sheet1!S109)>0 -> FALSE | K109: =COUNTIF('Duplicates_with_Master DB'!$A:$A,Sheet1!T109)>0 -> FALSE | L109: =M109 & IF(COUNTA(N109:T109), ", " & _xlfn.TEXTJOIN(", ", TRUE, N109:T109), "") -> 97823733 | M109: 97823733 | U109: lucas.ter@aonegroup.sg
A110: A-One Signature Chinatown Point | D110: =COUNTIF('Duplicates_with_Master DB'!$A:$A,Sheet1!M110)>0 -> FALSE | E110: =COUNTIF('Duplicates_with_Master DB'!$A:$A,Sheet1!N110)>0 -> FALSE | F110: =COUNTIF('Duplicates_with_Master DB'!$A:$A,Sheet1!O110)>0 -> FALSE | G110: =COUNTIF('Duplicates_with_Master DB'!$A:$A,Sheet1!P110)>0 -> FALSE | H110: =COUNTIF('Duplicates_with_Master DB'!$A:$A,Sheet1!Q110)>0 -> FALSE | I110: =COUNTIF('Duplicates_with_Master DB'!$A:$A,Sheet1!R110)>0 -> FALSE | J110: =COUNTIF('Duplicates_with_Master DB'!$A:$A,Sheet1!S110)>0 -> FALSE | K110: =COUNTIF('Duplicates_with_Master DB'!$A:$A,Sheet1!T110)>0 -> FALSE | L110: =M110 & IF(COUNTA(N110:T110), ", " & _xlfn.TEXTJOIN(", ", TRUE, N110:T110), "") -> 97823733 | M110: 97823733 | U110: lucas.ter@aonegroup.sg
A111: A-One Signature Compass One | D111: =COUNTIF('Duplicates_with_Master DB'!$A:$A,Sheet1!M111)>0 -> FALSE | E111: =COUNTIF('Duplicates_with_Master DB'!$A:$A,Sheet1!N111)>0 -> FALSE | F111: =COUNTIF('Duplicates_with_Master DB'!$A:$A,Sheet1!O111)>0 -> FALSE | G111: =COUNTIF('Duplicates_with_Master DB'!$A:$A,Sheet1!P111)>0 -> FALSE | H111: =COUNTIF('Duplicates_with_Master DB'!$A:$A,Sheet1!Q111)>0 -> FALSE | I111: =COUNTIF('Duplicates_with_Master DB'!$A:$A,Sheet1!R111)>0 -> FALSE | J111: =COUNTIF('Duplicates_with_Master DB'!$A:$A,Sheet1!S111)>0 -> FALSE | K111: =COUNTIF('Duplicates_with_Master DB'!$A:$A,Sheet1!T111)>0 -> FALSE | L111: =M111 & IF(COUNTA(N111:T111), ", " & _xlfn.TEXTJOIN(", ", TRUE, N111:T111), "") -> 97823733 | M111: 97823733 | U111: lucas.ter@aonegroup.sg
A112: A-One Signature JEM | D112: =COUNTIF('Duplicates_with_Master DB'!$A:$A,Sheet1!M112)>0 -> FALSE | E112: =COUNTIF('Duplicates_with_Master DB'!$A:$A,Sheet1!N112)>0 -> FALSE | F112: =COUNTIF('Duplicates_with_Master DB'!$A:$A,Sheet1!O112)>0 -> FALSE | G112: =COUNTIF('Duplicates_with_Master DB'!$A:$A,Sheet1!P112)>0 -> FALSE | H112: =COUNTIF('Duplicates_with_Master DB'!$A:$A,Sheet1!Q112)>0 -> FALSE | I112: =COUNTIF('Duplicates_with_Master DB'!$A:$A,Sheet1!R112)>0 -> FALSE | J112: =COUNTIF('Duplicates_with_Master DB'!$A:$A,Sheet1!S112)>0 -> FALSE | K112: =COUNTIF('Duplicates_with_Master DB'!$A:$A,Sheet1!T112)>0 -> FALSE | L112: =M112 & IF(COUNTA(N112:T112), ", " & _xlfn.TEXTJOIN(", ", TRUE, N112:T112), "") -> 97823733 | M112: 97823733 | U112: lucas.ter@aonegroup.sg, accounts.tabsquare@aonegroup.sg
A113: A-One Tampines 1 | D113: =COUNTIF('Duplicates_with_Master DB'!$A:$A,Sheet1!M113)>0 -> FALSE | E113: =COUNTIF('Duplicates_with_Master DB'!$A:$A,Sheet1!N113)>0 -> FALSE | F113: =COUNTIF('Duplicates_with_Master DB'!$A:$A,Sheet1!O113)>0 -> FALSE | G113: =COUNTIF('Duplicates_with_Master DB'!$A:$A,Sheet1!P113)>0 -> FALSE | H113: =COUNTIF('Duplicates_with_Master DB'!$A:$A,Sheet1!Q113)>0 -> FALSE | I113: =COUNTIF('Duplicates_with_Master DB'!$A:$A,Sheet1!R113)>0 -> FALSE | J113: =COUNTIF('Duplicates_with_Master DB'!$A:$A,Sheet1!S113)>0 -> FALSE | K113: =COUNTIF('Duplicates_with_Master DB'!$A:$A,Sheet1!T113)>0 -> FALSE | L113: =M113 & IF(COUNTA(N113:T113), ", " & _xlfn.TEXTJOIN(", ", TRUE, N113:T113), "") -> 97823733 | M113: 97823733 | U113: lucas.ter@aonegroup.sg
... A123: A-One Wester Tiong Bahru Plaza | D123: =COUNTIF('Duplicates_with_Master DB'!$A:$A,Sheet1!M123)>0 -> FALSE | E123: =COUNTIF('Duplicates_with_Master DB'!$A:$A,Sheet1!N123)>0 -> FALSE | F123: =COUNTIF('Duplicates_with_Master DB'!$A:$A,Sheet1!O123)>0 -> FALSE | G123: =COUNTIF('Duplicates_with_Master DB'!$A:$A,Sheet1!P123)>0 -> FALSE | H123: =COUNTIF('Duplicates_with_Master DB'!$A:$A,Sheet1!Q123)>0 -> FALSE | I123: =COUNTIF('Duplicates_with_Master DB'!$A:$A,Sheet1!R123)>0 -> FALSE | J123: =COUNTIF('Duplicates_with_Master DB'!$A:$A,Sheet1!S123)>0 -> FALSE | K123: =COUNTIF('Duplicates_with_Master DB'!$A:$A,Sheet1!T123)>0 -> FALSE | L123: =M123 & IF(COUNTA(N123:T123), ", " & _xlfn.TEXTJOIN(", ", TRUE, N123:T123), "") -> 97823733 | M123: 97823733 | U123: lucas.ter@aonegroup.sg
A124: A1 Famous Restaurant | D124: =COUNTIF('Duplicates_with_Master DB'!$A:$A,Sheet1!M124)>0 -> FALSE | E124: =COUNTIF('Duplicates_with_Master DB'!$A:$A,Sheet1!N124)>0 -> FALSE | F124: =COUNTIF('Duplicates_with_Master DB'!$A:$A,Sheet1!O124)>0 -> FALSE | G124: =COUNTIF('Duplicates_with_Master DB'!$A:$A,Sheet1!P124)>0 -> FALSE | H124: =COUNTIF('Duplicates_with_Master DB'!$A:$A,Sheet1!Q124)>0 -> FALSE | I124: =COUNTIF('Duplicates_with_Master DB'!$A:$A,Sheet1!R124)>0 -> FALSE | J124: =COUNTIF('Duplicates_with_Master DB'!$A:$A,Sheet1!S124)>0 -> FALSE | K124: =COUNTIF('Duplicates_with_Master DB'!$A:$A,Sheet1!T124)>0 -> FALSE | L124: =M124 & IF(COUNTA(N124:T124), ", " & _xlfn.TEXTJOIN(", ", TRUE, N124:T124), "")
A125: A2B Veg Restaurant | D125: =COUNTIF('Duplicates_with_Master DB'!$A:$A,Sheet1!M125)>0 -> FALSE | E125: =COUNTIF('Duplicates_with_Master DB'!$A:$A,Sheet1!N125)>0 -> FALSE | F125: =COUNTIF('Duplicates_with_Master DB'!$A:$A,Sheet1!O125)>0 -> FALSE | G125: =COUNTIF('Duplicates_with_Master DB'!$A:$A,Sheet1!P125)>0 -> FALSE | H125: =COUNTIF('Duplicates_with_Master DB'!$A:$A,Sheet1!Q125)>0 -> FALSE | I125: =COUNTIF('Duplicates_with_Master DB'!$A:$A,Sheet1!R125)>0 -> FALSE | J125: =COUNTIF('Duplicates_with_Master DB'!$A:$A,Sheet1!S125)>0 -> FALSE | K125: =COUNTIF('Duplicates_with_Master DB'!$A:$A,Sheet1!T125)>0 -> FALSE | L125: =M125 & IF(COUNTA(N125:T125), ", " & _xlfn.TEXTJOIN(", ", TRUE, N125:T125), "") -> 98804089 | M125: 98804089 | U125: Najeeba2b@gmail.com
A126: AAA Mokita Food Management & Catering Pte. Ltd. | D126: =COUNTIF('Duplicates_with_Master DB'!$A:$A,Sheet1!M126)>0 -> FALSE | E126: =COUNTIF('Duplicates_with_Master DB'!$A:$A,Sheet1!N126)>0 -> FALSE | F126: =COUNTIF('Duplicates_with_Master DB'!$A:$A,Sheet1!O126)>0 -> FALSE | G126: =COUNTIF('Duplicates_with_Master DB'!$A:$A,Sheet1!P126)>0 -> FALSE | H126: =COUNTIF('Duplicates_with_Master DB'!$A:$A,Sheet1!Q126)>0 -> FALSE | I126: =COUNTIF('Duplicates_with_Master DB'!$A:$A,Sheet1!R126)>0 -> FALSE | J126: =COUNTIF('Duplicates_with_Master DB'!$A:$A,Sheet1!S126)>0 -> FALSE | K126: =COUNTIF('Duplicates_with_Master DB'!$A:$A,Sheet1!T126)>0 -> FALSE | L126: =M126 & IF(COUNTA(N126:T126), ", " & _xlfn.TEXTJOIN(", ", TRUE, N126:T126), "") -> 91832482 | M126: 91832482 | U126: aaamokitachangi@gmail.com
...

Sheet Duplicates_with_Master DB
A1: number | B1: count_in_file1 | C1: count_in_file2
A2: 61006800 | B2: 1 | C2: 1
A3: 61234567 | B3: 2 | C3: 2
A4: 62046003 | B4: 1 | C4: 1
A5: 62134398 | B5: 2 | C5: 3
A6: 62134486 | B6: 1 | C6: 1
A7: 62134571 | B7: 1 | C7: 1
A8: 62212262 | B8: 2 | C8: 1
A9: 62212522 | B9: 1 | C9: 1
A10: 62213114 | B10: 1 | C10: 1
A11: 62213988 | B11: 1 | C11: 1
A12: 62214282 | B12: 1 | C12: 1
A13: 62216678 | B13: 1 | C13: 1
A14: 62217056 | B14: 1 | C14: 2
... A303: 98873377 | B303: 9 | C303: 1
